[
  {
    "title": "相无古今——石窟艺术超感沉浸体验",
    "name": "相无古今——石窟艺术超感沉浸体验",
    "venue": "浙江省博物馆之江馆",
    "city": "hangzhou",
    "start_date": "2026-01-01",
    "end_date": "2026-10-31",
    "link": "http://news.qq.com/rain/a/20250711A05A3P00",
    "url": "http://news.qq.com/rain/a/20250711A05A3P00",
    "description": "XR/AR/VR沉浸式石窟艺术展，利用数字技术还原石窟艺术之美。",
    "category": "展览",
    "fee": "部分免费",
    "contact": "",
    "family_friendly": true,
    "source": "腾讯新闻"
  },
  {
    "title": "古希腊的旅程——希腊31家博物馆文物展",
    "name": "古希腊的旅程——希腊31家博物馆文物展",
    "venue": "良渚博物院",
    "city": "hangzhou",
    "start_date": "2026-01-30",
    "end_date": "2026-07-31",
    "link": "https://www.lzmuseum.cn/LiangBoXinWen/2026974986977.html",
    "url": "https://www.lzmuseum.cn/LiangBoXinWen/2026974986977.html",
    "description": "希腊31家博物馆163件精品文物+9件复制品，跨文明对话大展，7月31日截止。",
    "category": "展览",
    "fee": "免费",
    "contact": "",
    "family_friendly": true,
    "source": "良渚博物院官网"
  },
  {
    "title": "绣美之江——浙江省刺绣、抽纱非遗艺术与生活作品展",
    "name": "绣美之江——浙江省刺绣、抽纱非遗艺术与生活作品展",
    "venue": "中国丝绸博物馆",
    "city": "hangzhou",
    "start_date": "2026-05-01",
    "end_date": "2026-11-16",
    "link": "http://wwj.zj.gov.cn/col/col1639083/art/2026/art_ab54c345895e4e73ab5490db53d0fdd0.html",
    "url": "http://wwj.zj.gov.cn/col/col1639083/art/2026/art_ab54c345895e4e73ab5490db53d0fdd0.html",
    "description": "近20项非遗刺绣项目，设连连看互动游戏，展示浙江刺绣抽纱传统技艺。",
    "category": "展览",
    "fee": "免费",
    "contact": "",
    "family_friendly": true,
    "source": "浙江省文化厅"
  },
  {
    "title": "湖山养心——从高濂进入明代西湖的生活美学",
    "name": "湖山养心——从高濂进入明代西湖的生活美学",
    "venue": "韩美林艺术馆",
    "city": "hangzhou",
    "start_date": "2026-05-18",
    "end_date": "2026-08-31",
    "link": "http://m.toutiao.com/group/7659690201555452467/",
    "url": "http://m.toutiao.com/group/7659690201555452467/",
    "description": "探讨明代戏曲作家高濂借西湖幽游以陶冶身心之法，展示《四时幽赏录》中西湖四时芳容。",
    "category": "展览",
    "fee": "免费",
    "contact": "",
    "family_friendly": false,
    "source": "杭州文旅发布"
  },
  {
    "title": "万物始兴·寒武纪化石展",
    "name": "万物始兴·寒武纪化石展",
    "venue": "浙江自然博物院",
    "city": "hangzhou",
    "start_date": "2026-06-01",
    "end_date": "2026-08-31",
    "link": "https://m.weibo.cn/detail/5318191891881429",
    "url": "https://m.weibo.cn/detail/5318191891881429",
    "description": "展出三叶虫、鱼龙、猛犸象化石骨架，配套化石挖掘体验、火山爆发科学实验秀、AR恐龙互动。",
    "category": "科普活动",
    "fee": "免费",
    "contact": "",
    "family_friendly": true,
    "source": "浙江自然博物院"
  },
  {
    "title": "纸见吴越——全国非遗剪纸优秀作品展",
    "name": "纸见吴越——全国非遗剪纸优秀作品展",
    "venue": "临安博物馆",
    "city": "hangzhou",
    "start_date": "2026-06-18",
    "end_date": "2026-10-07",
    "link": "http://m.toutiao.com/group/7659690201555452467/",
    "url": "http://m.toutiao.com/group/7659690201555452467/",
    "description": "分射潮安澜、以礼立城、钱氏遗韵、陌上花开四个单元，以剪纸方式重新唤醒吴越文化沉淀。",
    "category": "展览",
    "fee": "免费",
    "contact": "",
    "family_friendly": true,
    "source": "杭州文旅发布"
  },
  {
    "title": "印证千秋·河系大运——大运河主题篆刻艺术巡回邀请展",
    "name": "印证千秋·河系大运——大运河主题篆刻艺术巡回邀请展",
    "venue": "中国刀剪剑博物馆",
    "city": "hangzhou",
    "start_date": "2026-06-22",
    "end_date": "2026-07-21",
    "link": "http://m.toutiao.com/group/7659690201555452467/",
    "url": "http://m.toutiao.com/group/7659690201555452467/",
    "description": "以刀为笔，以石为纸，将绵延3200公里的大运河及其58处遗产点浓缩于方寸印章之间。",
    "category": "展览",
    "fee": "免费",
    "contact": "",
    "family_friendly": true,
    "source": "杭州文旅发布"
  },
  {
    "title": "一剑千年·《吴越国》纪录片主题特展",
    "name": "一剑千年·《吴越国》纪录片主题特展",
    "venue": "钱王祠",
    "city": "hangzhou",
    "start_date": "2026-06-24",
    "end_date": "2026-10-08",
    "link": "https://wgly.hangzhou.gov.cn/tc/zxzx/art/2026/art_200bef79bf84833eb885c42fb2027022.html",
    "url": "https://wgly.hangzhou.gov.cn/tc/zxzx/art/2026/art_200bef79bf84833eb885c42fb2027022.html",
    "description": "展出影片海报、原创服饰道具手稿、书法篆刻作品，配合实景沉浸式音乐剧《钱氏今生》演出。",
    "category": "展览",
    "fee": "收费",
    "contact": "",
    "family_friendly": true,
    "source": "杭州市文化广电旅游局"
  },
  {
    "title": "钱氏今生——实景沉浸式音乐剧",
    "name": "钱氏今生——实景沉浸式音乐剧",
    "venue": "钱王祠",
    "city": "hangzhou",
    "start_date": "2026-06-24",
    "end_date": "2026-10-08",
    "link": "https://wgly.hangzhou.gov.cn/tc/zxzx/art/2026/art_200bef79bf84833eb885c42fb2027022.html",
    "url": "https://wgly.hangzhou.gov.cn/tc/zxzx/art/2026/art_200bef79bf84833eb885c42fb2027022.html",
    "description": "以钱王浚湖治水功绩、《钱氏家训》传承为双主线，依托古祠实景演绎吴越文化与家风内涵。",
    "category": "演出",
    "fee": "收费",
    "contact": "",
    "family_friendly": true,
    "source": "杭州市文化广电旅游局"
  },
  {
    "title": "湖山之约，金石之美——西湖美学系列展",
    "name": "湖山之约，金石之美——西湖美学系列展",
    "venue": "杭州西湖博物馆",
    "city": "hangzhou",
    "start_date": "2026-06-24",
    "end_date": "2026-09-06",
    "link": "http://m.toutiao.com/group/7659690201555452467/",
    "url": "http://m.toutiao.com/group/7659690201555452467/",
    "description": "西湖与西泠携手，上溯先秦古印，近观西泠诸贤，金石气韵与湖山风骨水乳交融。",
    "category": "展览",
    "fee": "免费",
    "contact": "",
    "family_friendly": false,
    "source": "杭州文旅发布"
  },
  {
    "title": "月照银山：丝绸之路上的高昌与龟兹",
    "name": "月照银山：丝绸之路上的高昌与龟兹",
    "venue": "中国丝绸博物馆",
    "city": "hangzhou",
    "start_date": "2026-06-24",
    "end_date": "2026-09-01",
    "link": "https://tidenews.com.cn/news.html?id=3475919",
    "url": "https://tidenews.com.cn/news.html?id=3475919",
    "description": "2026丝绸之路周核心大展，200余件/组文物，展示丝绸之路上高昌与龟兹的文化交融。",
    "category": "展览",
    "fee": "免费",
    "contact": "",
    "family_friendly": true,
    "source": "潮新闻"
  },
  {
    "title": "故园有此声——张书旂艺术研究展",
    "name": "故园有此声——张书旂艺术研究展",
    "venue": "浙江省博物馆之江馆",
    "city": "hangzhou",
    "start_date": "2026-06-25",
    "end_date": "2026-07-23",
    "link": "https://bj.home.163.com/26/0624/16/L070QH4T08290024.html",
    "url": "https://bj.home.163.com/26/0624/16/L070QH4T08290024.html",
    "description": "文化和旅游部2025年全国美术馆青年策展人扶持计划入选项目，展示20世纪中国花鸟画大师张书旂的艺术成就。",
    "category": "展览",
    "fee": "免费",
    "contact": "",
    "family_friendly": false,
    "source": "浙江省博物馆"
  },
  {
    "title": "大道匠行——浙江工艺美术的历史经典与时代价值展",
    "name": "大道匠行——浙江工艺美术的历史经典与时代价值展",
    "venue": "杭州工艺美术博物馆",
    "city": "hangzhou",
    "start_date": "2026-06-26",
    "end_date": "2026-10-12",
    "link": "https://m.sohu.com/a/1046660218_121106994/",
    "url": "https://m.sohu.com/a/1046660218_121106994/",
    "description": "展示浙江工艺美术的历史经典与当代创新，手工体验区适合亲子参与（纸伞/剪纸/竹编等）。",
    "category": "亲子活动",
    "fee": "免费",
    "contact": "",
    "family_friendly": true,
    "source": "杭州市文旅局"
  },
  {
    "title": "太平年·天下同宁——交互艺术大展",
    "name": "太平年·天下同宁——交互艺术大展",
    "venue": "浙江省博物馆之江馆",
    "city": "hangzhou",
    "start_date": "2026-07-01",
    "end_date": "2026-08-31",
    "link": "https://wgly.hangzhou.gov.cn/tc/zxzx/art/2026/art_200bef79bf84833eb885c42fb2027022.html",
    "url": "https://wgly.hangzhou.gov.cn/tc/zxzx/art/2026/art_200bef79bf84833eb885c42fb2027022.html",
    "description": "融合实物文物、数字展陈与沉浸式演出的交互艺术大展，展现吴越文化太平年间的繁荣景象。杭州文旅消费季核心展览。",
    "category": "展览",
    "fee": "免费",
    "contact": "",
    "family_friendly": true,
    "source": "杭州市文化广电旅游局"
  },
  {
    "title": "一半勾留是此山——纪念韩登安先生逝世50周年作品展",
    "name": "一半勾留是此山——纪念韩登安先生逝世50周年作品展",
    "venue": "萧山博物馆",
    "city": "hangzhou",
    "start_date": "2026-07-01",
    "end_date": "2026-08-31",
    "link": "http://hznews.hangzhou.com.cn/wenti/content/2026-07/05/content_9249834.htm",
    "url": "http://hznews.hangzhou.com.cn/wenti/content/2026-07/05/content_9249834.htm",
    "description": "展出韩登安书画、篆刻、文献及门人作品百余件，完整梳理其艺术成就与浙派篆刻传承脉络。",
    "category": "展览",
    "fee": "免费",
    "contact": "",
    "family_friendly": false,
    "source": "杭州网"
  },
  {
    "title": "小书虫漫游记——杭图少儿分馆暑期活动",
    "name": "小书虫漫游记——杭图少儿分馆暑期活动",
    "venue": "杭州图书馆少儿分馆",
    "city": "hangzhou",
    "start_date": "2026-07-01",
    "end_date": "2026-08-31",
    "link": "https://wgly.hangzhou.gov.cn/tc/zxzx/art/2026/art_200bef79bf84833eb885c42fb2027022.html",
    "url": "https://wgly.hangzhou.gov.cn/tc/zxzx/art/2026/art_200bef79bf84833eb885c42fb2027022.html",
    "description": "联动全市400余家杭州书房开展的暑期少儿阅读活动，打造书香研学线路。",
    "category": "亲子活动",
    "fee": "免费",
    "contact": "",
    "family_friendly": true,
    "source": "杭州市文化广电旅游局"
  },
  {
    "title": "科学实验秀——浙江省科技馆暑期活动",
    "name": "科学实验秀——浙江省科技馆暑期活动",
    "venue": "浙江省科技馆",
    "city": "hangzhou",
    "start_date": "2026-07-01",
    "end_date": "2026-07-31",
    "link": "https://m.sohu.com/a/1044289750_121106994/",
    "url": "https://m.sohu.com/a/1044289750_121106994/",
    "description": "每天2场科学实验秀，含《寻心记》《物体的倔脾气》《静电碰撞》等十几个主题轮番上演。",
    "category": "科普活动",
    "fee": "免费",
    "contact": "",
    "family_friendly": true,
    "source": "浙江省科技馆"
  },
  {
    "title": "藓·苔藓微观世界展览",
    "name": "藓·苔藓微观世界展览",
    "venue": "浙江自然博物院安吉馆",
    "city": "hangzhou",
    "start_date": "2026-07-02",
    "end_date": "2026-10-31",
    "link": "https://m.sohu.com/a/1044374949_121107011/",
    "url": "https://m.sohu.com/a/1044374949_121107011/",
    "description": "沉浸式苔藓王国特展，展示微观世界里的植物多样性，适合自然爱好者。",
    "category": "展览",
    "fee": "免费",
    "contact": "",
    "family_friendly": true,
    "source": "搜狐"
  },
  {
    "title": "2026杭州奇妙夜——百日星悦游",
    "name": "2026杭州奇妙夜——百日星悦游",
    "venue": "天目里",
    "city": "hangzhou",
    "start_date": "2026-07-03",
    "end_date": "2026-10-10",
    "link": "https://wgly.hangzhou.gov.cn/tc/zxzx/art/2026/art_200bef79bf84833eb885c42fb2027022.html",
    "url": "https://wgly.hangzhou.gov.cn/tc/zxzx/art/2026/art_200bef79bf84833eb885c42fb2027022.html",
    "description": "3大夜主场+10大主题产品+全域联动营销夜游格局，集聚夜游科技、吴越文博、国潮市集等业态。",
    "category": "科普活动",
    "fee": "部分免费",
    "contact": "",
    "family_friendly": true,
    "source": "杭州市文化广电旅游局"
  },
  {
    "title": "考古探险队——杭州博物馆青少年模拟考古活动",
    "name": "考古探险队——杭州博物馆青少年模拟考古活动",
    "venue": "杭州博物馆",
    "city": "hangzhou",
    "start_date": "2026-07-05",
    "end_date": "2026-08-31",
    "link": "https://m.weibo.cn/detail/5317002210313637",
    "url": "https://m.weibo.cn/detail/5317002210313637",
    "description": "沉浸式触摸历史、探索地层、动手创造的青少年模拟考古活动，面向8-17岁青少年。",
    "category": "科普活动",
    "fee": "免费需预约",
    "contact": "",
    "family_friendly": true,
    "source": "杭州博物馆官方微博"
  },
  {
    "title": "撒马尔罕：中亚之心的千年古城特展",
    "name": "撒马尔罕：中亚之心的千年古城特展",
    "venue": "良渚博物院",
    "city": "hangzhou",
    "start_date": "2026-07-05",
    "end_date": "2026-07-31",
    "link": "https://www.lzmuseum.cn/LiangBoXinWen/2026385131382.html",
    "url": "https://www.lzmuseum.cn/LiangBoXinWen/2026385131382.html",
    "description": "26张精美照片展示中亚古城撒马尔罕的历史文化风貌，配合第34届书博会。",
    "category": "展览",
    "fee": "免费",
    "contact": "",
    "family_friendly": false,
    "source": "良渚博物院官网"
  },
  {
    "title": "机器狗AI编程夏令营",
    "name": "机器狗AI编程夏令营",
    "venue": "杭州图书馆",
    "city": "hangzhou",
    "start_date": "2026-07-07",
    "end_date": "2026-07-31",
    "link": "https://www.zjhzlib.cn/hdyghz/8010.htm",
    "url": "https://www.zjhzlib.cn/hdyghz/8010.htm",
    "description": "四期连开的机器狗AI编程夏令营，面向7岁以上少儿，通过编程控制机器狗完成任务。",
    "category": "科普活动",
    "fee": "免费",
    "contact": "",
    "family_friendly": true,
    "source": "杭州图书馆官网"
  },
  {
    "title": "秉灯照麒麟——八一七稻米季系列活动",
    "name": "秉灯照麒麟——八一七稻米季系列活动",
    "venue": "西泠·武林美术馆",
    "city": "hangzhou",
    "start_date": "2026-07-08",
    "end_date": "2026-08-17",
    "link": "http://hznews.hangzhou.com.cn/wenti/content/2026-07/05/content_9249834.htm",
    "url": "http://hznews.hangzhou.com.cn/wenti/content/2026-07/05/content_9249834.htm",
    "description": "推出重磅影视道具展览，盗墓笔记IP热门场景二白茶馆、南部档案风味馆惊喜亮相。",
    "category": "展览",
    "fee": "收费",
    "contact": "",
    "family_friendly": false,
    "source": "杭州网"
  },
  {
    "title": "欢迎来到恐龙时代——知识视界科普讲座",
    "name": "欢迎来到恐龙时代——知识视界科普讲座",
    "venue": "杭州图书馆少儿分馆",
    "city": "hangzhou",
    "start_date": "2026-07-16",
    "end_date": "2026-07-16",
    "link": "https://www.zjhzlib.cn/hdyghz/8010.htm",
    "url": "https://www.zjhzlib.cn/hdyghz/8010.htm",
    "description": "杭小图看世界系列科普讲座，带领少儿读者探索恐龙时代的奥秘，需通过浙里文化圈报名。",
    "category": "讲座阅读",
    "fee": "免费",
    "contact": "86535086",
    "family_friendly": true,
    "source": "杭州图书馆官网"
  },
  {
    "title": "2026年茶人之家亲子公益培训（二期）",
    "name": "2026年茶人之家亲子公益培训（二期）",
    "venue": "中国茶叶博物馆",
    "city": "hangzhou",
    "start_date": "2026-07-16",
    "end_date": "2026-07-19",
    "link": "https://m.sohu.com/a/1038933302_121107011/",
    "url": "https://m.sohu.com/a/1038933302_121107011/",
    "description": "四天17节亲子课程，涵盖茶文化、茶叶冲泡、茶礼仪等，面向亲子家庭。",
    "category": "亲子活动",
    "fee": "免费",
    "contact": "",
    "family_friendly": true,
    "source": "中国茶叶博物馆"
  },
  {
    "title": "亲子共学·慧学慧成长（第三期）英语中的神奇魔法",
    "name": "亲子共学·慧学慧成长（第三期）英语中的神奇魔法",
    "venue": "杭州图书馆",
    "city": "hangzhou",
    "start_date": "2026-07-19",
    "end_date": "2026-07-19",
    "link": "https://www.zjhzlib.cn/hdyghz/8010.htm",
    "url": "https://www.zjhzlib.cn/hdyghz/8010.htm",
    "description": "成长体验营亲子共学系列活动，通过趣味英语学习激发孩子语言兴趣，面向亲子家庭。",
    "category": "亲子活动",
    "fee": "免费",
    "contact": "86535079",
    "family_friendly": true,
    "source": "杭州图书馆官网"
  },
  {
    "title": "第34届全国书博会",
    "name": "第34届全国书博会",
    "venue": "杭州国际博览中心",
    "city": "hangzhou",
    "start_date": "2026-07-24",
    "end_date": "2026-07-27",
    "link": "https://wgly.hangzhou.gov.cn/tc/zxzx/art/2026/art_200bef79bf84833eb885c42fb2027022.html",
    "url": "https://wgly.hangzhou.gov.cn/tc/zxzx/art/2026/art_200bef79bf84833eb885c42fb2027022.html",
    "description": "八大展厅、九大专题展览、十一项重点活动，发放300万元惠民购书券，打造暑期书香盛宴。",
    "category": "展览",
    "fee": "免费",
    "contact": "",
    "family_friendly": true,
    "source": "杭州市文化广电旅游局"
  },
  {
    "title": "穿越古都历史，解锁文物密码——阅读分享会",
    "name": "穿越古都历史，解锁文物密码——阅读分享会",
    "venue": "杭州图书馆少儿分馆",
    "city": "hangzhou",
    "start_date": "2026-07-25",
    "end_date": "2026-07-25",
    "link": "https://www.zjhzlib.cn/hdyghz/8010.htm",
    "url": "https://www.zjhzlib.cn/hdyghz/8010.htm",
    "description": "杭小图阅童年系列活动，通过阅读分享会形式带领少儿穿越古都历史，解锁文物背后的密码故事。",
    "category": "讲座阅读",
    "fee": "免费",
    "contact": "87962447",
    "family_friendly": true,
    "source": "杭州图书馆官网"
  }
]