[
  {
    "title": "世界树之巅：美洲古代文明大展",
    "venue": "上海博物馆人民广场馆",
    "city": "shanghai",
    "start_date": "2026-07-09",
    "end_date": "2027-11-14",
    "link": "https://www.shanghaimuseum.net/mu/frontend/pg/article/id/I00005037",
    "description": "上海博物馆继金字塔之巅后又一重磅巨献，联合墨西哥、秘鲁顶尖文博机构，汇聚1129组近3000件精美文物，全景式勾勒古代中南美洲的文明长卷，打造全球史上规模最大、等级最高的美洲古代文明大展。展陈空间超7000平方米，分为神圣时空和黄金帝国两大板块。",
    "fee": "收费（全价票148元，亲子票适用于6-14周岁儿童）",
    "source": "上海博物馆官网",
    "family_friendly": true
  },
  {
    "title": "世界树之巅——美洲古代文明大展动物奇妙夜",
    "venue": "上海博物馆人民广场馆",
    "city": "shanghai",
    "start_date": "2026-07-09",
    "end_date": "2026-08-31",
    "link": "https://m.sh.bendibao.com/tour/307215.html",
    "description": "上海博物馆与上海动物园联手打造的夜场活动，每周六晚举行。复刻亚马逊湿地、热带雨林等美洲原生生态场景，引入水豚、羊驼、龙猫等美洲特色动物互动，含原创音乐短剧《Hi, YAX!》及中庭唤醒仪式。",
    "fee": "收费（基础活动票198元/人）",
    "source": "上海本地宝",
    "family_friendly": true
  },
  {
    "title": "千金之家——马王堆汉墓的生活美学及养成国宝艺术大展",
    "venue": "上海美术馆（中华艺术宫）",
    "city": "shanghai",
    "start_date": "2026-07-03",
    "end_date": "2026-10-07",
    "link": "https://whlyj.sh.gov.cn/wlyw/20260702/2dbbdd4047684d548deff8720480fd2f.html",
    "description": "马王堆50余年考古研究史上规模最大、等级最高的一次湖南省外展出，展现汉代生活的极致风雅。以纹样之眼、器用之序、天人之思三大篇章，呈现两千年前西汉社会的精致日常与文化魅力。",
    "fee": "收费（购票参与）",
    "source": "上海市文化和旅游局",
    "family_friendly": true
  },
  {
    "title": "国采——故宫藏清代帝后服饰展",
    "venue": "上海世博会博物馆",
    "city": "shanghai",
    "start_date": "2026-07-07",
    "end_date": "2026-10-07",
    "link": "https://www.meet-in-shanghai.net/cn/news/the-2026-shanghai-tourism-festival-summer-tourism-season-kicks-off-on-july-8-170-activities-and-six-major-themed-weeks-are-online-388024/",
    "description": "世博会博物馆携手故宫博物院推出，含康熙礼服褂、乾隆龙袍、嘉庆朝袍等101件织绣文物，九成从未出京，超三成首次面世。设在上海看见故宫数字体验展区，运用VR、裸眼3D等技术打造九大互动展项。",
    "fee": "收费（普通票88元、双人票138元、优待票68元、儿童票9.9元）",
    "source": "乐游上海",
    "family_friendly": true
  },
  {
    "title": "肇兴中国：秦·大一统之路文物考古特展",
    "venue": "上海博物馆东馆",
    "city": "shanghai",
    "start_date": "2026-06-01",
    "end_date": "2026-09-07",
    "link": "https://whlyj.sh.gov.cn/wlyw/20260702/2dbbdd4047684d548deff8720480fd2f.html",
    "description": "何以中国文物考古大展系列第五展，由上海博物馆、甘肃省文物考古研究所、陕西省考古研究院主办，汇集来自14家文博机构的300多套文物，以考古实证勾勒秦人从部族崛起到一统天下的壮阔历程。",
    "fee": "免费（需预约）",
    "source": "上海市文化和旅游局",
    "family_friendly": true
  },
  {
    "title": "头号玩家解锁大秦逆袭之路",
    "venue": "上海博物馆东馆",
    "city": "shanghai",
    "start_date": "2026-07-16",
    "end_date": "2026-08-31",
    "link": "https://paper.xinmin.cn/html/xmwb/2026-07-17/13/243348.html",
    "description": "上博学院暑期研学活动，孩子们化身少年秦王，在博物馆展厅中寻找秦统一天下的六大物质条件，用一整天的所学所感，亲手设计属于自己的历史策略桌游。",
    "fee": "收费（研学营）",
    "source": "新民晚报",
    "family_friendly": true
  },
  {
    "title": "我在上博修文物之瓷器金缮",
    "venue": "上海博物馆",
    "city": "shanghai",
    "start_date": "2026-07-01",
    "end_date": "2026-08-31",
    "link": "https://paper.xinmin.cn/html/xmwb/2026-07-17/13/243348.html",
    "description": "上博学院暑期研学活动，除传统看展、了解文物故事外，孩子还能对瓷器工艺、修复过程和类型有基础认知，在上海博物馆专属教室深入观摩修复流程与步骤，展厅主题导赏加手作体验。",
    "fee": "收费（研学营）",
    "source": "新民晚报",
    "family_friendly": true
  },
  {
    "title": "当莫兰迪遇上传统中国色——东西方色彩大PK",
    "venue": "上海博物馆东馆",
    "city": "shanghai",
    "start_date": "2026-07-01",
    "end_date": "2026-08-31",
    "link": "https://paper.xinmin.cn/html/xmwb/2026-07-17/13/243348.html",
    "description": "上博学院夏令营联动浦东美术馆，孩子们在专业导师讲解下观察莫兰迪画面色调，再转场上博东馆陶瓷馆，以瓷器里的绝美中国色为线索，比较中西方美学气质，含艺术疗愈色彩实验。",
    "fee": "收费（夏令营）",
    "source": "新民晚报",
    "family_friendly": true
  },
  {
    "title": "世界树之灵·美洲萌萌TA奇妙夜",
    "venue": "上海博物馆人民广场馆",
    "city": "shanghai",
    "start_date": "2026-07-11",
    "end_date": "2026-08-31",
    "link": "https://m.toutiao.com/group/7663498228075954751/",
    "description": "上博为小观众度身定制的活动，贯穿整个暑假。小朋友在观展之余可打卡上海博物馆联合上海动物园专门打造的美洲动物生态展厅，复刻安第斯山脉、亚马孙湿地、热带雨林、荒漠等美洲原生地貌，设美洲动物科普讲解。",
    "fee": "收费（基础活动票198元/人，单场限额3000人）",
    "source": "新民晚报",
    "family_friendly": true
  },
  {
    "title": "邮轮出游记——青少年科普展",
    "venue": "中国航海博物馆",
    "city": "shanghai",
    "start_date": "2026-06-01",
    "end_date": "2026-09-20",
    "link": "http://m.toutiao.com/group/7662955572609696292/",
    "description": "上海市2026年百展百课官方认证项目，位于中国航海博物馆三层风帆厅，能学邮轮文化、解锁航海科技，让孩子体验科普课堂和模拟讲解，锻炼胆量、提升气质。",
    "fee": "收费（博物馆门票30元/人）",
    "source": "上海体育",
    "family_friendly": true
  },
  {
    "title": "上海体育博物馆博物馆奇妙夜主题活动",
    "venue": "上海体育博物馆",
    "city": "shanghai",
    "start_date": "2026-07-01",
    "end_date": "2026-08-31",
    "link": "http://m.toutiao.com/group/7662955572609696292/",
    "description": "7月在奇妙夜享受夜间观展与定时讲解，8月更有特邀资深汽车设计师带大家探秘汽车设计美学，主题讲座、趣味分享轮番上阵。开放时间7-8月每周五16:30-20:30。",
    "fee": "免费（免门票免预约）",
    "source": "上海体育",
    "family_friendly": true
  },
  {
    "title": "森林职业体验·水质净化家",
    "venue": "共青森林公园",
    "city": "shanghai",
    "start_date": "2026-07-01",
    "end_date": "2026-08-31",
    "link": "http://m.toutiao.com/group/7662955572609696292/",
    "description": "面向6-15岁亲子家庭，在共青森林公园生态课堂里，孩子们化身专业的水质净化家，学习检测水质的方法，感受水体的超能力，为构建健康的水下生态系统出力。",
    "fee": "收费",
    "source": "上海体育",
    "family_friendly": true
  },
  {
    "title": "史前星球：恐龙篇沉浸式巨幕体验",
    "venue": "西岸美术馆",
    "city": "shanghai",
    "start_date": "2026-06-27",
    "end_date": "2027-01-27",
    "link": "https://www.meet-in-shanghai.net/cn/news/the-2026-shanghai-tourism-festival-summer-tourism-season-kicks-off-on-july-8-170-activities-and-six-major-themed-weeks-are-online-388024/",
    "description": "改编自纪录片Prehistoric Planet史前星球，精选第一、第二季经典场景，通过先进的360度沉浸式投影系统，参与者与史前生物同行，在空间中真实感受它们的尺度、行为与生存环境。亚洲首展，1:1还原史前恐龙。",
    "fee": "收费（详见OUTPUT EXPERIENCE公众号）",
    "source": "乐游上海",
    "family_friendly": true
  },
  {
    "title": "动物奇妙夜",
    "venue": "上海动物园",
    "city": "shanghai",
    "start_date": "2026-07-01",
    "end_date": "2026-08-31",
    "link": "https://www.meet-in-shanghai.net/cn/news/the-2026-shanghai-tourism-festival-summer-tourism-season-kicks-off-on-july-8-170-activities-and-six-major-themed-weeks-are-online-388024/",
    "description": "探秘夜间动物园，增设夜猫子和森林课夜观活动，展示动物园内夜行性动物难得一见的自然行为，丰富戏水和夜游体验。",
    "fee": "收费（详见上海动物园公众号）",
    "source": "乐游上海",
    "family_friendly": true
  },
  {
    "title": "虎鲸造浪节暑期主题活动",
    "venue": "上海海昌海洋公园",
    "city": "shanghai",
    "start_date": "2026-06-27",
    "end_date": "2026-08-31",
    "link": "https://www.meet-in-shanghai.net/cn/news/the-2026-shanghai-tourism-festival-summer-tourism-season-kicks-off-on-july-8-170-activities-and-six-major-themed-weeks-are-online-388024/",
    "description": "连续66天夜场，围绕4大戏水、7大剧目升级、奥特曼60周年庆、烟花盛典等特色活动，7月11日-8月23日更有虎鲸造浪音乐节嗨翻全场。室内20度恒温海洋场馆搭配室外造浪戏水。",
    "fee": "收费（成人特惠票199元，儿童特惠票59.9元）",
    "source": "乐游上海",
    "family_friendly": true
  },
  {
    "title": "科好玩了——2026暑假营",
    "venue": "上海科技馆",
    "city": "shanghai",
    "start_date": "2026-06-27",
    "end_date": "2026-08-31",
    "link": "https://content-static.cctvnews.cctv.com/snow-book/index.html?channelId=777&item_id=14758528641071581094&toc_style_id=feeds_default",
    "description": "集结15大特色科普品牌，覆盖球幕沉浸式多媒体互动秀、科创实践营、VR数字剧场等多元内容，以兼具趣味性、前沿性、艺术性的科普供给，打造沉浸式夏日科学体验营。每周六延时开放至20:00，推出古风NPC巡游、文创市集、机器人互动、灯光秀等夜间活动。",
    "fee": "收费（需预约）",
    "source": "央视新闻",
    "family_friendly": true
  },
  {
    "title": "粒子奇遇球幕多媒体互动展演",
    "venue": "上海科技馆",
    "city": "shanghai",
    "start_date": "2026-06-27",
    "end_date": "2026-08-31",
    "link": "https://content-static.cctvnews.cctv.com/snow-book/index.html?channelId=777&item_id=14758528641071581094&toc_style_id=feeds_default",
    "description": "在全新升级的上海科技馆球幕影院开展，融合真人讲解、舞台表演、原创音乐与全景画面。观众跟随叙事进入微观世界，了解原子核裂变、核聚变、夸克、中微子等知识，适配全年龄段观众。",
    "fee": "收费（需购买上海科技馆门票）",
    "source": "央视新闻",
    "family_friendly": true
  },
  {
    "title": "上海科普大讲坛第242期——江门中微子实验科普首发专场",
    "venue": "上海科技馆",
    "city": "shanghai",
    "start_date": "2026-06-27",
    "end_date": "2026-06-27",
    "link": "https://content-static.cctvnews.cctv.com/snow-book/index.html?channelId=777&item_id=14758528641071581094&toc_style_id=feeds_default",
    "description": "特邀上海交通大学江门中微子刻度团队孟月教授现场分享，面向公众通俗拆解这项世界级科研成果，深度解读精确测量中微子振荡参数对粒子物理、宇宙探索的深远意义。该成果作为封面文章刊发于国际顶级期刊Nature。",
    "fee": "免费（需预约）",
    "source": "央视新闻",
    "family_friendly": true
  },
  {
    "title": "巴斯夫小小化学家——电池的奥秘",
    "venue": "上海科技馆",
    "city": "shanghai",
    "start_date": "2026-07-13",
    "end_date": "2026-08-31",
    "link": "http://www.sh.chinanews.com/kjjj/2026-07-13/147673.shtml",
    "description": "广受儿童及家长喜爱的年度公益科普活动，聚焦电化学主题，45分钟的趣味实验电池的奥秘适合6-12周岁的孩子。志愿者引导孩子们选择合适的电极材料和电解质，搭建原电池架构，感受电能的来之不易。设有电化学主题陈设，展示不同电池发展历史。",
    "fee": "免费（公益）",
    "source": "中新网上海",
    "family_friendly": true
  },
  {
    "title": "乐高玩乐节",
    "venue": "上海乐高乐园度假区",
    "city": "shanghai",
    "start_date": "2026-06-11",
    "end_date": "2026-08-31",
    "link": "https://www.shanghai.gov.cn/nw17239/20260622/ca85991680884f8f89f6efc86da449f3.html",
    "description": "首次登陆中国的乐高玩乐节，乐园开辟约4000平方米全新区域，打造五大主题区，通过携手FIFA世界杯和F1两大IP，以丰富的互动游戏、创意拼搭体验、特色演出等，为游客带来融合潮流与创意的夏日玩乐嘉年华。",
    "fee": "收费（乐园门票，早鸟优惠一日票339元）",
    "source": "上海市人民政府",
    "family_friendly": true
  },
  {
    "title": "上海乐高乐园度假区一周年庆典及夜光大派对",
    "venue": "上海乐高乐园度假区",
    "city": "shanghai",
    "start_date": "2026-07-05",
    "end_date": "2026-08-30",
    "link": "https://www.shanghai.gov.cn/nw15343/20260701/dc4b539ee7e34955a9a263590b247050.html",
    "description": "7月5日启动一周年庆典，开启为期两个月生日活动。每周五、六、日夜间，乐园特别上演无人机互动表演，1000架次无人机方阵变换队形。傍晚园内灯光秀准时点亮，游船河道、小火车底部、竹林等区域灯光与环境交织。",
    "fee": "收费（乐园门票）",
    "source": "上海市人民政府",
    "family_friendly": true
  },
  {
    "title": "上海迪士尼乐园夏日缤纷主题体验",
    "venue": "上海迪士尼乐园",
    "city": "shanghai",
    "start_date": "2026-07-01",
    "end_date": "2026-08-31",
    "link": "http://m.sh.bendibao.com/tour/jd/307624.html",
    "description": "上海迪士尼开业十周年限定夏日狂欢。即日起至8月1日每周五、周六重磅上线加时升级日，乐园延时至22:30。明日世界化身高燃舞池举办夏日音浪派对，限定金色光效创极速光轮全新亮相，水花巡游沿路喷洒清凉水雾，城堡上演十周年特别幻影秀，新增无人机编队特效。",
    "fee": "收费（乐园门票）",
    "source": "上海本地宝",
    "family_friendly": true
  },
  {
    "title": "上海野生动物园全新夏日野趣夜游",
    "venue": "上海野生动物园",
    "city": "shanghai",
    "start_date": "2026-07-01",
    "end_date": "2026-08-31",
    "link": "http://m.sh.bendibao.com/tour/jd/307624.html",
    "description": "夜公园持续开放至21:00，以日游狂欢+夜探秘境双线模式打造都市野趣夜游体验。傍晚乘水域探秘游船穿梭林间湖面，近距离观赏金丝猴、河马、黑帽悬猴的黄昏日常。全园光影装置同步点亮，萤火星河、百兽夜行等场景铺满园区，联动蛋仔派对主题打卡装置。",
    "fee": "收费（暑期特惠成人票118元，夜场票99元）",
    "source": "上海本地宝",
    "family_friendly": true
  },
  {
    "title": "东方明珠钛空明珠星舰体验空间",
    "venue": "东方明珠电视塔",
    "city": "shanghai",
    "start_date": "2026-07-01",
    "end_date": "2026-12-31",
    "link": "http://m.sh.bendibao.com/tour/jd/307624.html",
    "description": "位于东方明珠电视塔98米与107米区域，围绕航天发射、轨道飞行、火星探测与深空漫游打造的高空太空主题体验空间。游客以星际旅客的身份进入一场完整的太空任务，经历发射升空、星际飞行、火星探索与深空返航。",
    "fee": "收费",
    "source": "上海本地宝",
    "family_friendly": true
  },
  {
    "title": "邂逅星空夜场活动",
    "venue": "上海天文馆",
    "city": "shanghai",
    "start_date": "2026-07-04",
    "end_date": "2026-08-30",
    "link": "http://m.sh.bendibao.com/tour/307215.html",
    "description": "上海天文馆夜间品牌活动，7月4日、12日、19日、26日及8月指定日期开放。主打4小时全流程沉浸体验，覆盖展区导览、天象厅模拟、球幕观影与户外观测四大模块，使用国内最大的科普级一米望远镜。",
    "fee": "收费（358元/人，携程预约）",
    "source": "上海本地宝",
    "family_friendly": true
  },
  {
    "title": "趣玩博物馆奇妙夜暑期专场——夜宿上海自然博物馆",
    "venue": "上海自然博物馆",
    "city": "shanghai",
    "start_date": "2026-07-11",
    "end_date": "2026-08-22",
    "link": "http://m.online.sh.cn/hot/content/2026-07/03/content_10465654.htm",
    "description": "7月11日、25日，8月8日、22日17:00至次日7:30，亲子家庭可在自然博物馆内搭帐篷夜宿，与恐龙、猛犸象、剑齿虎等史前巨兽的化石标本或模型同眠。参加恐龙、蝴蝶主题科普+手工活动，跟随专业科普人员逛馆，欣赏科普电影和亲子音乐会。",
    "fee": "收费（夜宿专场）",
    "source": "上海发布",
    "family_friendly": true
  },
  {
    "title": "江河联山海·无界结万象上历博博物馆奇妙夜系列活动",
    "venue": "上海市历史博物馆（上海革命历史博物馆）",
    "city": "shanghai",
    "start_date": "2026-07-01",
    "end_date": "2026-08-31",
    "link": "http://m.sh.bendibao.com/tour/307215.html",
    "description": "包括小浪花讲解团带领青少年以童声讲述苏州河故事；苏州河夜游Citywalk线路用脚步丈量水系变迁；徽州非遗工坊主题文化研学活动等。西楼临展厅延长开放至20:00，配合博物馆奇妙夜时间段文创区销售8.8折。",
    "fee": "免费&收费都有（微信公众号预约）",
    "source": "上海本地宝",
    "family_friendly": true
  },
  {
    "title": "从元代水闸到外白渡桥——苏州河历史文化展",
    "venue": "上海市历史博物馆",
    "city": "shanghai",
    "start_date": "2026-07-01",
    "end_date": "2026-08-31",
    "link": "http://m.sh.bendibao.com/tour/307215.html",
    "description": "上海历史博物馆暑期特展之一，作为博物馆奇妙夜系列活动配套展览，呈现苏州河的历史文化变迁。",
    "fee": "免费（需预约）",
    "source": "上海本地宝",
    "family_friendly": true
  },
  {
    "title": "只在山林与泉曲——徽州文化艺术展",
    "venue": "上海市历史博物馆",
    "city": "shanghai",
    "start_date": "2026-07-01",
    "end_date": "2026-08-31",
    "link": "http://m.sh.bendibao.com/tour/307215.html",
    "description": "上海历史博物馆暑期特展之一，展示徽州文化艺术，配合徽州非遗工坊主题文化研学活动。",
    "fee": "免费（需预约）",
    "source": "上海本地宝",
    "family_friendly": true
  },
  {
    "title": "乒乓体验营",
    "venue": "国际乒联博物馆和中国乒乓球博物馆",
    "city": "shanghai",
    "start_date": "2026-07-08",
    "end_date": "2026-07-16",
    "link": "http://m.sh.bendibao.com/tour/307215.html",
    "description": "面向中小学生的免费乒乓体验营，7月8日和7月16日开展，需通过国际乒联博物馆和中国乒乓球博物馆微信公众号预约。",
    "fee": "免费（需预约）",
    "source": "上海本地宝",
    "family_friendly": true
  },
  {
    "title": "豫享山林夜游豫园",
    "venue": "上海豫园",
    "city": "shanghai",
    "start_date": "2026-07-01",
    "end_date": "2026-08-31",
    "link": "http://m.sh.bendibao.com/tour/307215.html",
    "description": "7月1日至8月31日期间，每周二、三、五、六、日19:00-21:50（21:00停止检票入园）开放夜游豫园，需通过上海豫园微信小程序预约。",
    "fee": "收费",
    "source": "上海本地宝",
    "family_friendly": true
  },
  {
    "title": "清韵——康雍乾时期文物特展",
    "venue": "闵行博物馆",
    "city": "shanghai",
    "start_date": "2026-07-01",
    "end_date": "2026-09-01",
    "link": "http://m.toutiao.com/group/7659366256658645504/",
    "description": "携手中国文物交流中心、中国国家博物馆、中国丝绸博物馆、首都博物馆、沈阳故宫博物院等15家文博单位，汇集110余件（套）珍贵文物，重现公元17至18世纪中国手工业的巅峰技艺与时代审美。暑期开放四场夜场，含免费夜间定时讲解和盖章打卡活动。",
    "fee": "免费",
    "source": "新闻晨报",
    "family_friendly": true
  },
  {
    "title": "宝硕流光——故宫博物院藏乾隆时期文物特展",
    "venue": "奉贤博物馆",
    "city": "shanghai",
    "start_date": "2026-06-01",
    "end_date": "2026-11-18",
    "link": "http://m.toutiao.com/group/7662711103108989440/",
    "description": "展出121件（套）故宫珍藏，涵盖金银器、瓷器、玉器、漆器、文房、织绣、佛供、武备等，件件都是乾隆皇帝生前珍视的心头好。从御玺、朝袍，到亲自督造的双连瓶、三色玻璃瓶，再到私藏的古董字画、西洋钟表，全景还原乾隆执政生涯与精神世界。",
    "fee": "免费（无需预约，现场参观）",
    "source": "新闻晨报",
    "family_friendly": true
  },
  {
    "title": "守时成器——当代工艺美术邀请展",
    "venue": "嘉定博物馆",
    "city": "shanghai",
    "start_date": "2026-06-12",
    "end_date": "2026-07-12",
    "link": "http://wenlv.jiading.cn/bwg/jbzx/content_967509",
    "description": "由嘉定区文化和旅游局和上海工艺美术职业学院主办，展出近100件作品，涵盖大漆工艺、陶瓷工艺、黄杨木雕、玻璃工艺、木刻版画等非遗手工技艺，还增设古建筑遗产、文物修复、古籍修复、中国水墨、当代雕塑，以及手工艺艺术疗愈板块。",
    "fee": "免费（直接前往参观即可）",
    "source": "嘉定博物馆",
    "family_friendly": true
  },
  {
    "title": "水浒传——赵溶油画作品展及小小油画修复师活动工坊",
    "venue": "嘉定博物馆",
    "city": "shanghai",
    "start_date": "2026-07-16",
    "end_date": "2026-08-16",
    "link": "http://wenlv.jiading.cn/bwg/jbzx/content_970058",
    "description": "展览期间推出小小油画修复师活动工坊，专业修复师团队亲授，微缩油画亲手修复，成品可带回家。让未成年人亲手修复艺术时光，解锁潮酷文化体验。8月1日13:30-15:00开展活动。另有夜谈水浒夜间定时讲解、石塑粘土冰箱贴等亲子手作活动。",
    "fee": "免费",
    "source": "嘉定博物馆",
    "family_friendly": true
  },
  {
    "title": "小小消防员奇妙夜暑期消防科普专项活动",
    "venue": "上海消防博物馆",
    "city": "shanghai",
    "start_date": "2026-07-18",
    "end_date": "2026-08-08",
    "link": "http://m.toutiao.com/group/7659366256658645504/",
    "description": "亲子共学护成长——小小消防员奇妙夜，7月18日、25日面向3-6周岁亲子家庭，8月1日、8日面向7-12周岁亲子家庭，1大1小，每组15组家庭，现场报名登记或电话预约。7-8月延时开放到20时。",
    "fee": "免费",
    "source": "新闻晨报",
    "family_friendly": true
  },
  {
    "title": "地学集市",
    "venue": "上海观止矿晶博物馆",
    "city": "shanghai",
    "start_date": "2026-07-05",
    "end_date": "2026-08-16",
    "link": "http://m.toutiao.com/group/7659366256658645504/",
    "description": "7月5日（有集市）、7月17日、8月16日（有集市）09:30-11:30、13:00-19:00开放，举办地学集市活动，面向全市市民，无需预约。文创产品全部9折、盖纪念章、买即赠小宝石。",
    "fee": "免费",
    "source": "新闻晨报",
    "family_friendly": true
  },
  {
    "title": "亲子酷玩：彩绘汉纹样热缩片国风挂件",
    "venue": "上海美术馆（中华艺术宫）",
    "city": "shanghai",
    "start_date": "2026-07-11",
    "end_date": "2026-07-15",
    "link": "http://m.toutiao.com/group/7661942638341276198/",
    "description": "邀请小朋友和爸爸妈妈一起欣赏千金之家中的纹样之美，将喜欢的纹样绘在热缩片上，通过串珠与编绳，创作汉纹样彩绘国风挂件。15组亲子家庭，微信免费预约。",
    "fee": "免费（微信免费预约）",
    "source": "上海美术馆",
    "family_friendly": true
  },
  {
    "title": "亲子酷玩：T形帛画里的天地人皮影工作坊",
    "venue": "上海美术馆（中华艺术宫）",
    "city": "shanghai",
    "start_date": "2026-07-26",
    "end_date": "2026-07-26",
    "link": "http://m.toutiao.com/group/7660191712152699407/",
    "description": "结合千金之家马王堆汉墓展览中的T形帛画主题，开展的亲子皮影工作坊活动，通过上海美术馆中华艺术宫微信公众号报名。",
    "fee": "免费（需预约）",
    "source": "新民晚报",
    "family_friendly": true
  },
  {
    "title": "千金之家马王堆之穿深衣的贵族对谈活动",
    "venue": "上海美术馆（中华艺术宫）",
    "city": "shanghai",
    "start_date": "2026-07-28",
    "end_date": "2026-07-28",
    "link": "http://m.toutiao.com/group/7660191712152699407/",
    "description": "围绕千金之家展览中的马王堆文化主题，邀请艺术文化领域大咖，从服饰制度、礼仪生活与身份象征等角度展开对谈，带领观众走近汉代贵族生活与审美世界。",
    "fee": "免费（需预约）",
    "source": "新民晚报",
    "family_friendly": true
  },
  {
    "title": "走近程十发——循迹瑶寨·水彩人物写生体验",
    "venue": "上海中国画院程十发美术馆",
    "city": "shanghai",
    "start_date": "2026-07-11",
    "end_date": "2026-07-18",
    "link": "http://m.toutiao.com/group/7660191712152699407/",
    "description": "7月11日和7月18日14:00开展，通过上海中国画院微信公众号预约报名（预约开放时间7月9日、7月16日10:00）。",
    "fee": "免费（需预约）",
    "source": "新民晚报",
    "family_friendly": true
  },
  {
    "title": "走近非遗——马到成功·松江布艺手作活动",
    "venue": "上海中国画院程十发美术馆",
    "city": "shanghai",
    "start_date": "2026-07-12",
    "end_date": "2026-07-19",
    "link": "http://m.toutiao.com/group/7660191712152699407/",
    "description": "7月12日、7月19日15:00开展，通过上海中国画院微信公众号预约报名（预约开放时间7月10日、7月17日10:00）。",
    "fee": "免费（需预约）",
    "source": "新民晚报",
    "family_friendly": true
  },
  {
    "title": "墨染清风·执扇纳凉手绘团扇体验",
    "venue": "上海中国画院美术馆",
    "city": "shanghai",
    "start_date": "2026-07-16",
    "end_date": "2026-07-17",
    "link": "http://m.toutiao.com/group/7660191712152699407/",
    "description": "7月16日14:00-15:30、7月17日18:30-20:00开展，通过上海中国画院微信公众号预约报名。",
    "fee": "免费（需预约）",
    "source": "新民晚报",
    "family_friendly": true
  },
  {
    "title": "夏日露营·声音帐篷",
    "venue": "刘海粟美术馆",
    "city": "shanghai",
    "start_date": "2026-07-17",
    "end_date": "2026-07-18",
    "link": "http://m.toutiao.com/group/7660191712152699407/",
    "description": "邀请孩子们一起在美术馆里露营，用木头和布织出一座巨大的、毛茸茸的、会呼吸的蚕茧，叫《声音帐篷》。这不是一次简单的搭建，而是一场关于自然、材料与声音的深度共创。7月17日、18日10:00-16:00，通过刘海粟美术馆微信公众号报名。",
    "fee": "免费（需预约）",
    "source": "新民晚报",
    "family_friendly": true
  },
  {
    "title": "捏一尊自己的石膏像——立体头像工作坊",
    "venue": "刘海粟美术馆",
    "city": "shanghai",
    "start_date": "2026-07-26",
    "end_date": "2026-07-26",
    "link": "http://m.toutiao.com/group/7660191712152699407/",
    "description": "7月26日13:30-15:00开展，通过刘海粟美术馆微信公众号报名。",
    "fee": "免费（需预约）",
    "source": "新民晚报",
    "family_friendly": true
  },
  {
    "title": "莫兰迪工作坊——色彩实验室",
    "venue": "浦东美术馆",
    "city": "shanghai",
    "start_date": "2026-07-26",
    "end_date": "2026-07-26",
    "link": "http://m.toutiao.com/group/7660191712152699407/",
    "description": "7月26日14:00-15:00开展，调配莫兰迪色系，为陶盆上色，并完成绿植种植，体验色彩之间细腻的层次变化。线上预约，需购买美术馆门票。",
    "fee": "收费（需购买美术馆门票）",
    "source": "新民晚报",
    "family_friendly": true
  },
  {
    "title": "浦东美术馆五周年BLOOM IN MAP绽放在浦美",
    "venue": "浦东美术馆",
    "city": "shanghai",
    "start_date": "2026-07-01",
    "end_date": "2026-08-31",
    "link": "http://m.toutiao.com/group/7662382031741682216/",
    "description": "五周年主题艺术装置在馆内和滨江沿线陆续上线，包括1F大厅共创笑脸墙、五周年装置打卡。惊喜俱乐部系列快闪演艺、绽美生活系列活动（速写东岸、摇摆舞会、音律八段锦等），参与活动无需额外付费，部分活动名额有限先到先得。",
    "fee": "免费（部分活动需购买美术馆门票）",
    "source": "新民晚报",
    "family_friendly": true
  },
  {
    "title": "2026科学会堂·牛顿苹果树夏令营——探寻四时观物候",
    "venue": "上海科学会堂",
    "city": "shanghai",
    "start_date": "2026-08-12",
    "end_date": "2026-08-13",
    "link": "https://www.shobserver.cn/sgh/detail?id=4022052",
    "description": "以天地物候与生命科学为核心主线，两日串联观天候→识药材→知科学→践真知完整认知链条，带领8-12岁少年读懂自然时序。包含自然时序主题分享、五彩中草药辨识、儿童急救安全实训、独立创作观察笔记、动手制作专属作品、亲自体验气象主播。报名满15人开营。",
    "fee": "收费（夏令营）",
    "source": "上观新闻",
    "family_friendly": true
  },
  {
    "title": "小小考古家·妇好鸮尊挖宝乐手作体验",
    "venue": "黄浦文化中心",
    "city": "shanghai",
    "start_date": "2026-07-06",
    "end_date": "2026-07-06",
    "link": "https://www.jfdaily.com/sgh/detail?id=4014398",
    "description": "艺美黄浦·艺门课程暑期美育夏令营亲子手作活动，带小朋友们解锁国宝妇好鸮尊的前世今生，了解商代青铜文物的造型之美与历史内涵，并亲手组装妇好鸮尊模型。7月6日10:00，黄浦文化中心701综合活动室，20组（一大一小）。",
    "fee": "免费（需预约）",
    "source": "上观新闻",
    "family_friendly": true
  },
  {
    "title": "小小考古家·竹简DIY手作体验",
    "venue": "黄浦文化中心",
    "city": "shanghai",
    "start_date": "2026-07-13",
    "end_date": "2026-07-13",
    "link": "https://www.jfdaily.com/sgh/detail?id=4014398",
    "description": "艺美黄浦·艺门课程暑期美育夏令营亲子手作活动，小朋友们可以亲手打磨、拼装、装饰专属竹简，既能锻炼动手能力，又能感受中华传统文化的古老智慧。7月13日10:00，20组（一大一小）。",
    "fee": "免费（需预约）",
    "source": "上观新闻",
    "family_friendly": true
  },
  {
    "title": "小小考古家·清明上河图胶囊拼图手作体验",
    "venue": "黄浦文化中心",
    "city": "shanghai",
    "start_date": "2026-07-20",
    "end_date": "2026-07-20",
    "link": "https://www.jfdaily.com/sgh/detail?id=4014398",
    "description": "艺美黄浦·艺门课程暑期美育夏令营亲子手作活动，老师拆解名画清明上河图中的经典场景，为孩子们讲解宋代民俗、建筑、市井生活小知识，让小朋友们在耐心拼装的同时，沉浸式感受名画的魅力。7月20日10:00，20组（一大一小）。",
    "fee": "免费（需预约）",
    "source": "上观新闻",
    "family_friendly": true
  },
  {
    "title": "小小考古家·青花瓷贴片杯垫手作体验",
    "venue": "黄浦文化中心",
    "city": "shanghai",
    "start_date": "2026-07-27",
    "end_date": "2026-07-27",
    "link": "https://www.jfdaily.com/sgh/detail?id=4014398",
    "description": "艺美黄浦·艺门课程暑期美育夏令营亲子手作活动，老师带领大家了解青花瓷的发展历史、纹样寓意与传统工艺。小朋友动手搭配青花贴片，亲手创意拼接出独一无二的专属杯垫。7月27日10:00，20组（一大一小）。",
    "fee": "免费（需预约）",
    "source": "上观新闻",
    "family_friendly": true
  },
  {
    "title": "小小拼装家·石库门民居拼搭手作体验",
    "venue": "黄浦文化中心",
    "city": "shanghai",
    "start_date": "2026-07-08",
    "end_date": "2026-07-08",
    "link": "https://www.jfdaily.com/sgh/detail?id=4014398",
    "description": "艺美黄浦·艺门课程暑期美育夏令营亲子手作活动，老师带孩子们了解石库门建筑的特色、历史背景与人文故事。小朋友化身小小建筑家，亲手拼搭复古石库门民居模型。7月8日10:00，20组（一大一小）。",
    "fee": "免费（需预约）",
    "source": "上观新闻",
    "family_friendly": true
  },
  {
    "title": "小小拼装家·外白渡桥拼搭手作体验",
    "venue": "黄浦文化中心",
    "city": "shanghai",
    "start_date": "2026-07-15",
    "end_date": "2026-07-15",
    "link": "https://www.jfdaily.com/sgh/detail?id=4014398",
    "description": "艺美黄浦·艺门课程暑期美育夏令营亲子手作活动，为孩子们讲解外白渡桥的建筑特点、百年历史故事。从零开始亲手拼装桥梁模型，解锁桥梁建筑小知识。7月15日10:00，20组（一大一小）。",
    "fee": "免费（需预约）",
    "source": "上观新闻",
    "family_friendly": true
  },
  {
    "title": "小小拼装家·红色地标手作体验",
    "venue": "黄浦文化中心",
    "city": "shanghai",
    "start_date": "2026-07-22",
    "end_date": "2026-07-22",
    "link": "https://www.jfdaily.com/sgh/detail?id=4014398",
    "description": "艺美黄浦·艺门课程暑期美育夏令营亲子手作活动，依托黄浦本土红色文化资源，老师带领孩子们了解上海经典红色地标的历史故事与革命情怀。通过手工拼装红色建筑模型，让枯燥的历史知识变得生动有趣。7月22日10:00，20组（一大一小）。",
    "fee": "免费（需预约）",
    "source": "上观新闻",
    "family_friendly": true
  },
  {
    "title": "物理趣味小课堂：光影变变变·纸杯投影大冒险",
    "venue": "静安区图书馆闻喜路馆",
    "city": "shanghai",
    "start_date": "2026-07-01",
    "end_date": "2026-08-31",
    "link": "http://m.toutiao.com/group/7663442840953618950/",
    "description": "讲师以影院银幕等生活中的光影为切入点，抛出光会不会拐弯的趣味问题。孩子们手持纸杯、透明胶带与彩笔，低头勾勒星星、小动物图案，细心粘贴、裁剪组装简易投影装置。待到室内灯光熄灭，手绘图案清晰投射在墙面。",
    "fee": "免费",
    "source": "新民晚报",
    "family_friendly": true
  },
  {
    "title": "静安区图书馆沪语文化训练营",
    "venue": "静安区图书馆",
    "city": "shanghai",
    "start_date": "2026-07-01",
    "end_date": "2026-08-31",
    "link": "http://m.toutiao.com/group/7663442840953618950/",
    "description": "面向5至12岁亲子家庭，以童谣、绕口令等传递海派方言魅力。静安区图书馆今年暑期打造六大活动系列，推出近50场活动，覆盖3至12岁小读者。",
    "fee": "免费",
    "source": "新民晚报",
    "family_friendly": true
  },
  {
    "title": "宝山区图书馆邮轮原创绘本巡展与亲子故事会",
    "venue": "宝山区图书馆",
    "city": "shanghai",
    "start_date": "2026-07-01",
    "end_date": "2026-08-31",
    "link": "http://m.toutiao.com/group/7663442840953618950/",
    "description": "宝山区图书馆暑期活动深度扎根区域邮轮、非遗、红色滨江特色。馆内开展邮轮原创绘本巡展与亲子故事会，擦亮宝山邮轮文化名片。",
    "fee": "免费",
    "source": "新民晚报",
    "family_friendly": true
  },
  {
    "title": "儿童剧《魔法岛》宝山区图书馆线下演出",
    "venue": "宝山区图书馆",
    "city": "shanghai",
    "start_date": "2026-07-01",
    "end_date": "2026-08-31",
    "link": "http://m.toutiao.com/group/7663442840953618950/",
    "description": "宝山区图书馆暑期活动，儿童剧《魔法岛》等线下演出，为暑期增添了文艺氛围感。联动区内文化场馆，开展研学与实践，科普工坊、非遗手工坊、经典文学讲座、亲子绘本故事会轮番上线。",
    "fee": "免费",
    "source": "新民晚报",
    "family_friendly": true
  },
  {
    "title": "杨浦区图书馆Science童创营",
    "venue": "杨浦区图书馆",
    "city": "shanghai",
    "start_date": "2026-07-01",
    "end_date": "2026-08-31",
    "link": "http://m.toutiao.com/group/7663442840953618950/",
    "description": "7月、8月分别推出食虫植物生态盒制作、海洋水母手工，树立生态保护理念。传统文化板块以《大中华寻宝记》为载体，解读秦代三秦文化、丝路甘肃诗词等。",
    "fee": "免费",
    "source": "新民晚报",
    "family_friendly": true
  },
  {
    "title": "探索古代神奇科技：地下长城坎儿井",
    "venue": "长宁区图书馆天山馆",
    "city": "shanghai",
    "start_date": "2026-07-03",
    "end_date": "2026-07-03",
    "link": "https://whlyj.sh.gov.cn/gqfc/20260703/fd3affa588db423aa629b09f2791764d.html",
    "description": "长图暑期夜读·夜游·夜赏系列活动，7月3日18:30在长宁区图书馆天山馆10楼活动中厅开展，适合6-10岁亲子家庭。",
    "fee": "免费（需关注上海市长宁区图书馆微信公众号）",
    "source": "上海市文化和旅游局",
    "family_friendly": true
  },
  {
    "title": "苏河故事在长宁",
    "venue": "长宁区图书馆天山馆",
    "city": "shanghai",
    "start_date": "2026-07-10",
    "end_date": "2026-07-10",
    "link": "https://whlyj.sh.gov.cn/gqfc/20260703/fd3affa588db423aa629b09f2791764d.html",
    "description": "长图暑期夜读·夜游·夜赏系列活动，7月10日18:30在长宁区图书馆天山馆10楼活动中厅开展，适合6-10岁亲子家庭。",
    "fee": "免费（需关注上海市长宁区图书馆微信公众号）",
    "source": "上海市文化和旅游局",
    "family_friendly": true
  },
  {
    "title": "第八届长三角当代水墨典籍入画系列展之林泉高致导赏+寻觅传统色彩之美体验活动",
    "venue": "长宁区图书馆天山馆",
    "city": "shanghai",
    "start_date": "2026-07-17",
    "end_date": "2026-07-17",
    "link": "https://whlyj.sh.gov.cn/gqfc/20260703/fd3affa588db423aa629b09f2791764d.html",
    "description": "长图暑期夜读·夜游·夜赏系列活动，7月17日18:00在长宁区图书馆天山馆3楼展厅开展，适合6-10岁亲子家庭。",
    "fee": "免费（需关注上海市长宁区图书馆微信公众号）",
    "source": "上海市文化和旅游局",
    "family_friendly": true
  },
  {
    "title": "诗词里的长征精神",
    "venue": "长宁区图书馆天山馆",
    "city": "shanghai",
    "start_date": "2026-07-22",
    "end_date": "2026-07-22",
    "link": "https://whlyj.sh.gov.cn/gqfc/20260703/fd3affa588db423aa629b09f2791764d.html",
    "description": "长图暑期夜读·夜游·夜赏系列活动，7月22日18:30在长宁区图书馆天山馆10楼活动中厅开展，适合6-10岁亲子家庭。",
    "fee": "免费（需关注上海市长宁区图书馆微信公众号）",
    "source": "上海市文化和旅游局",
    "family_friendly": true
  },
  {
    "title": "探寻传统纹样的秘密",
    "venue": "长宁区图书馆天山馆",
    "city": "shanghai",
    "start_date": "2026-07-24",
    "end_date": "2026-07-24",
    "link": "https://whlyj.sh.gov.cn/gqfc/20260703/fd3affa588db423aa629b09f2791764d.html",
    "description": "长图暑期夜读·夜游·夜赏系列活动，7月24日18:30在长宁区图书馆天山馆3楼展厅开展，适合6-10岁亲子家庭。",
    "fee": "免费（需关注上海市长宁区图书馆微信公众号）",
    "source": "上海市文化和旅游局",
    "family_friendly": true
  },
  {
    "title": "传统文化中的家国情怀",
    "venue": "长宁区图书馆天山馆",
    "city": "shanghai",
    "start_date": "2026-07-29",
    "end_date": "2026-07-29",
    "link": "https://whlyj.sh.gov.cn/gqfc/20260703/fd3affa588db423aa629b09f2791764d.html",
    "description": "长图暑期夜读·夜游·夜赏系列活动，7月29日18:30在长宁区图书馆天山馆10楼活动中厅开展，适合6-10岁亲子家庭。",
    "fee": "免费（需关注上海市长宁区图书馆微信公众号）",
    "source": "上海市文化和旅游局",
    "family_friendly": true
  },
  {
    "title": "2026年长耳兔阅兔长跑阅读打卡线上赛",
    "venue": "长宁区图书馆",
    "city": "shanghai",
    "start_date": "2026-07-01",
    "end_date": "2026-10-31",
    "link": "https://whlyj.sh.gov.cn/gqfc/20260703/fd3affa588db423aa629b09f2791764d.html",
    "description": "青少年暑期读书月活动，在长宁区图书馆微信订阅号平台开展，适合6-10岁亲子家庭，扫描二维码参赛。",
    "fee": "免费",
    "source": "上海市文化和旅游局",
    "family_friendly": true
  },
  {
    "title": "书香可品味·悦读漫长宁——2026巡游长图打卡活动",
    "venue": "长宁区商圈、文化地标和文商旅融合点位",
    "city": "shanghai",
    "start_date": "2026-07-18",
    "end_date": "2026-08-23",
    "link": "https://whlyj.sh.gov.cn/gqfc/20260703/fd3affa588db423aa629b09f2791764d.html",
    "description": "深受广大读者喜爱的长图文化品牌活动，将在长宁的地标商圈内持续举办，读者们将会感受到不同于图书馆的全新文化体验，适合全年龄段市民、读者、亲子家庭。",
    "fee": "免费",
    "source": "上海市文化和旅游局",
    "family_friendly": true
  },
  {
    "title": "宁趣成长·童趣收音机制作",
    "venue": "长宁区妇女儿童服务指导中心",
    "city": "shanghai",
    "start_date": "2026-07-02",
    "end_date": "2026-07-02",
    "link": "https://www.shanghai.gov.cn/nw17239/20260701/4e274b24372542ceb244ad44655efc7d.html",
    "description": "探索简单电路原理，动手组装童趣收音机元器件，认识基础电子配件，调试组装专属小收音机，在动手实践中感受科学乐趣，锻炼逻辑思维与动手能力。7月2日14:00，亲子家庭。",
    "fee": "免费（公益活动，需报名）",
    "source": "上海市人民政府",
    "family_friendly": true
  },
  {
    "title": "宁趣成长·手绘光影玻璃杯",
    "venue": "长宁区妇女儿童服务指导中心",
    "city": "shanghai",
    "start_date": "2026-07-16",
    "end_date": "2026-07-16",
    "link": "https://www.shanghai.gov.cn/nw17239/20260701/4e274b24372542ceb244ad44655efc7d.html",
    "description": "7月16日上午开展，面向亲子家庭，通过长宁女性公众号参与报名。",
    "fee": "免费（公益活动，需报名）",
    "source": "上海市人民政府",
    "family_friendly": true
  },
  {
    "title": "宁趣成长·跟着文物做钥匙扣",
    "venue": "长宁区妇女儿童服务指导中心",
    "city": "shanghai",
    "start_date": "2026-07-29",
    "end_date": "2026-07-29",
    "link": "https://www.shanghai.gov.cn/nw17239/20260701/4e274b24372542ceb244ad44655efc7d.html",
    "description": "7月29日上午开展，面向亲子家庭，通过长宁女性公众号参与报名。",
    "fee": "免费（公益活动，需报名）",
    "source": "上海市人民政府",
    "family_friendly": true
  },
  {
    "title": "驭空飞艇·模筑山河——静安区少年宫暑期模型菁英营",
    "venue": "静安区少年宫",
    "city": "shanghai",
    "start_date": "2026-07-01",
    "end_date": "2026-08-31",
    "link": "http://m.toutiao.com/group/7662978466429567522/",
    "description": "四十名营员齐聚少年宫，用两天时间搭建微缩景观、组装遥控氦气飞艇，解锁一场从地面到高空的上海地标巡游挑战。复刻九曲桥、徐浦大桥、东方明珠、天宫牌楼等四大主题布景，开展遥控氦气飞艇组装与地标巡游挑战赛。",
    "fee": "免费（公益）",
    "source": "静安区少年宫",
    "family_friendly": true
  },
  {
    "title": "2026闵行区学生暑期公益开放活动",
    "venue": "闵行区青少年活动中心",
    "city": "shanghai",
    "start_date": "2026-07-14",
    "end_date": "2026-07-18",
    "link": "https://www.163.com/dy/article/L1B1STI30534B3IC.html",
    "description": "闵行区青少年活动中心携手39家学校少年宫精心准备线下特色项目，以暑期公益性开放性活动的形式，为大家带来科技、艺术、运动等各类精彩丰富的互动体验。上午场9:30-11:00，下午场13:30-15:00，共10场。面向闵行区小学三年级及以上学生。",
    "fee": "免费（随申办App线上报名）",
    "source": "上海闵行",
    "family_friendly": true
  },
  {
    "title": "AI创未来·2026全国青少年上海研学营",
    "venue": "上海市青少年活动中心",
    "city": "shanghai",
    "start_date": "2026-07-01",
    "end_date": "2026-08-31",
    "link": "https://m.sohu.com/a/1043912374_121106854/",
    "description": "由中国青少年宫协会指导，上海市青少年活动中心主办，亲临世界人工智能大会，参加WAIC青少年创新发展论坛，探秘WAIC前沿AI科技展。登顶上海中心大厦探究阻尼器黑科技，走进上海航宇科普中心、上海交通大学。5天4晚，3880元/人，面向全国10-16岁青少年。",
    "fee": "收费（3880元/人）",
    "source": "包头市青少年活动中心",
    "family_friendly": true
  },
  {
    "title": "滴水湖帆船体验",
    "venue": "滴水湖帆船俱乐部",
    "city": "shanghai",
    "start_date": "2026-07-01",
    "end_date": "2026-08-31",
    "link": "http://m.toutiao.com/group/7662955572609696292/",
    "description": "作为上海最大的人工湖泊，滴水湖拥有规整的河道和得天独厚的地理优势，是上海著名的水上运动胜地。带孩子体验皮划艇或OP级帆船，在专业教练的指导下，学习穿戴救生衣、认识船体结构，掌握基础划桨或控帆技巧。",
    "fee": "收费",
    "source": "上海体育",
    "family_friendly": true
  },
  {
    "title": "大宁公园荷花主题游园会",
    "venue": "大宁公园",
    "city": "shanghai",
    "start_date": "2026-07-18",
    "end_date": "2026-08-02",
    "link": "http://m.sh.bendibao.com/tour/307613.html",
    "description": "以花开夏时，荷夜未央为主题，全程免票，每周末设夜游专场，日间赏荷韵，夜间享流光。",
    "fee": "免费",
    "source": "上海本地宝",
    "family_friendly": true
  },
  {
    "title": "放鹤谷千灯会",
    "venue": "放鹤谷鲜花农场",
    "city": "shanghai",
    "start_date": "2026-07-01",
    "end_date": "2026-08-30",
    "link": "http://m.sh.bendibao.com/tour/307613.html",
    "description": "本次灯会引进国家级非遗四川自贡灯会，将园区50亩花田升级为梦幻灯海，解锁白天赏花、夜晚观灯的夏日游玩模式。",
    "fee": "收费",
    "source": "上海本地宝",
    "family_friendly": true
  },
  {
    "title": "2026佘山度假区盛夏狂欢季",
    "venue": "上海佘山国家旅游度假区",
    "city": "shanghai",
    "start_date": "2026-07-01",
    "end_date": "2026-08-31",
    "link": "http://m.sh.bendibao.com/tour/307613.html",
    "description": "以趣佘山 GO狂欢为主题，推出七大主题板块、二十余项特色活动，覆盖青年潮玩、亲子游乐、自然研学、竞速赛事、夏令营及特色美食，并同步推出高铁票根专属惠民福利。",
    "fee": "收费",
    "source": "上海本地宝",
    "family_friendly": true
  },
  {
    "title": "上海庄行伏羊美食嘉年华",
    "venue": "花米庄行景区",
    "city": "shanghai",
    "start_date": "2026-07-01",
    "end_date": "2026-09-10",
    "link": "http://m.sh.bendibao.com/tour/307613.html",
    "description": "联动内蒙古、宁夏特色羊肉参展，设有全羊宴市集、草地Live、光影秀与水岸集市，打造三伏天食补夜游盛宴。",
    "fee": "免费（市集免票）",
    "source": "上海本地宝",
    "family_friendly": true
  },
  {
    "title": "历史的星辉——长安画派与海派绘画研究展",
    "venue": "上海美术馆（中华艺术宫）",
    "city": "shanghai",
    "start_date": "2026-07-16",
    "end_date": "2026-09-16",
    "link": "http://m.sh.bendibao.com/tour/307613.html",
    "description": "聚焦新中国成立后中国画的革新与发展，呈现两大画派同中有异的艺术路径。",
    "fee": "免费",
    "source": "上海本地宝",
    "family_friendly": true
  },
  {
    "title": "CHINA白——白瓷艺术展",
    "venue": "上海世界技能博物馆",
    "city": "shanghai",
    "start_date": "2026-07-16",
    "end_date": "2026-10-31",
    "link": "http://m.sh.bendibao.com/tour/307613.html",
    "description": "汇集中国工艺美术大师等数十位业界领军人物的100余件白瓷艺术瑰宝。",
    "fee": "收费",
    "source": "上海本地宝",
    "family_friendly": true
  },
  {
    "title": "玻璃应力：流动的威尼斯狂欢",
    "venue": "上海久事美术馆",
    "city": "shanghai",
    "start_date": "2026-07-18",
    "end_date": "2026-10-18",
    "link": "http://m.sh.bendibao.com/tour/307613.html",
    "description": "邀请来自全球近20个国家的约50位艺术家参展，揭示艺术家与玻璃材料的抵抗、合作与联结。",
    "fee": "收费",
    "source": "上海本地宝",
    "family_friendly": true
  },
  {
    "title": "塑我此生：贾科梅蒂艺术大展",
    "venue": "上海民生现代美术馆",
    "city": "shanghai",
    "start_date": "2026-07-17",
    "end_date": "2026-12-06",
    "link": "http://m.sh.bendibao.com/tour/307613.html",
    "description": "汇集212件重量级藏品与珍贵档案资料，完整覆盖20世纪传奇艺术家阿尔贝托·贾科梅蒂的创作全周期。",
    "fee": "收费",
    "source": "上海本地宝",
    "family_friendly": true
  },
  {
    "title": "陈世英：他界之器",
    "venue": "龙美术馆（西岸馆）",
    "city": "shanghai",
    "start_date": "2026-07-18",
    "end_date": "2026-10-25",
    "link": "http://m.sh.bendibao.com/tour/307613.html",
    "description": "以三件巨型钛金属雕塑为核心，梳理陈世英近年来的钛金属雕塑创作脉络。",
    "fee": "收费",
    "source": "上海本地宝",
    "family_friendly": true
  },
  {
    "title": "上海玛雅海滩水公园夏浪戏水节",
    "venue": "上海玛雅海滩水公园",
    "city": "shanghai",
    "start_date": "2026-06-14",
    "end_date": "2026-08-31",
    "link": "http://m.sh.bendibao.com/tour/jd/307624.html",
    "description": "2026夏浪戏水节6月14日已启幕，六大亲子闯关项目、深海龙宫NPC天团亮相。40余项水上项目，24小时活水循环，水质安全，全家嗨玩一整天。",
    "fee": "收费（毕业生优惠票160元，大中小学生票180元）",
    "source": "上海本地宝",
    "family_friendly": true
  },
  {
    "title": "廊下夏日果蔬美食季系列活动",
    "venue": "廊下郊野公园",
    "city": "shanghai",
    "start_date": "2026-05-29",
    "end_date": "2026-08-31",
    "link": "https://www.shanghai.gov.cn/nw17239/20260622/ca85991680884f8f89f6efc86da449f3.html",
    "description": "随着桃子、葡萄、金山小皇冠西瓜等陆续上市，廊下郊野公园进入甜蜜果蔬季，陆续推出吃瓜大赛、果蔬采摘、摸鱼钓虾、天幕露营等相关活动。",
    "fee": "收费（部分活动免费）",
    "source": "上海市人民政府",
    "family_friendly": true
  },
  {
    "title": "金山蟠桃宴",
    "venue": "吕巷水果公园",
    "city": "shanghai",
    "start_date": "2026-07-19",
    "end_date": "2026-08-19",
    "link": "https://www.shanghai.gov.cn/nw17239/20260622/ca85991680884f8f89f6efc86da449f3.html",
    "description": "金山蟠桃季邂逅AI机器人，周末爆点演出精彩纷呈。AI环节主打沉浸式观赏，感受科技魅力；融合潮流音乐、民俗市集，打造乡村游首选地。看AI、听音乐、逛集市，一站尽享。",
    "fee": "收费",
    "source": "上海市人民政府",
    "family_friendly": true
  },
  {
    "title": "非遗里的人生智慧——金山嘴渔村非遗体验",
    "venue": "金山嘴渔村",
    "city": "shanghai",
    "start_date": "2026-07-04",
    "end_date": "2026-08-31",
    "link": "https://www.shanghai.gov.cn/nw17239/20260622/ca85991680884f8f89f6efc86da449f3.html",
    "description": "非遗里的养生（7月4日-5日、7月11日-12日），在金山嘴非遗市集制作香囊、养生锤，感悟非遗技艺与中华本草的养生哲学。非遗里的渔家技艺（8月每周六、日），现场展示渔家传统技艺，体验织渔网、拼装船模、品海鲜。",
    "fee": "免费（市集免票）",
    "source": "上海市人民政府",
    "family_friendly": true
  },
  {
    "title": "阅夜乐动听——金山区图书馆奇妙夜系列活动",
    "venue": "金山区图书馆",
    "city": "shanghai",
    "start_date": "2026-07-01",
    "end_date": "2026-08-31",
    "link": "https://www.shanghai.gov.cn/nw17239/20260622/ca85991680884f8f89f6efc86da449f3.html",
    "description": "金山区图书馆暑期推出奇妙夜系列活动，围绕社会大美育，策划金山诗词主题音乐会、儿童剧互动演出、学生才艺展示秀等丰富多彩的创新活动，旨在吸引更多读者走进图书馆。",
    "fee": "免费",
    "source": "上海市人民政府",
    "family_friendly": true
  },
  {
    "title": "跟着非遗去旅行——金山区博物馆暑期研学夏令营",
    "venue": "金山区博物馆",
    "city": "shanghai",
    "start_date": "2026-07-01",
    "end_date": "2026-08-31",
    "link": "https://www.shanghai.gov.cn/nw17239/20260622/ca85991680884f8f89f6efc86da449f3.html",
    "description": "为更好展示金山区独特而丰富的非遗资源，促进文旅深度融合，金山区博物馆推出跟着非遗去旅行暑期研学夏令营活动。",
    "fee": "收费（夏令营）",
    "source": "上海市人民政府",
    "family_friendly": true
  },
  {
    "title": "神马都好玩——当达拉木马遇见中国非遗展览",
    "venue": "世界会客厅（北外滩）",
    "city": "shanghai",
    "start_date": "2026-06-14",
    "end_date": "2026-08-31",
    "link": "https://www.shhk.gov.cn/slh/038001/20260528/0e057840-28e7-4441-9126-980aca04544f.html",
    "description": "恰逢中瑞建交76周年、农历马年双重契机，以瑞典达拉木马为文化纽带，联动全国优质非遗资源。黄浦江畔落地14米高创基尼斯纪录的达拉木马雕塑，集结20项全国马主题非遗技艺，含竹编机器马。展期内开展52场多元文化活动，涵盖非遗市集、戏曲导赏、手工体验、文化讲堂等。",
    "fee": "收费（早鸟票单人69元、双人129元；正价票及优待票）",
    "source": "上海市虹口区人民政府",
    "family_friendly": true
  },
  {
    "title": "趣野一夏Park Cycling夏日户外探索季",
    "venue": "嘉北郊野公园",
    "city": "shanghai",
    "start_date": "2026-07-01",
    "end_date": "2026-08-31",
    "link": "https://whlyj.sh.gov.cn/wlyw/20260702/2dbbdd4047684d548deff8720480fd2f.html",
    "description": "嘉北郊野公园推出趣野一夏Park Cycling夏日户外探索季，远郊乡野打造户外亲子探索体验。",
    "fee": "收费",
    "source": "上海市文化和旅游局",
    "family_friendly": true
  },
  {
    "title": "盛夏伏羊夜·热血足球季",
    "venue": "崇明长兴岛郊野公园",
    "city": "shanghai",
    "start_date": "2026-07-01",
    "end_date": "2026-08-31",
    "link": "https://whlyj.sh.gov.cn/wlyw/20260702/2dbbdd4047684d548deff8720480fd2f.html",
    "description": "崇明长兴岛郊野公园打造盛夏伏羊夜·热血足球季，融合伏羊美食与足球运动，远郊乡野夏日活动。",
    "fee": "收费",
    "source": "上海市文化和旅游局",
    "family_friendly": true
  },
  {
    "title": "Meow, Cats! @ The British Library",
    "venue": "上海图书馆东馆",
    "city": "shanghai",
    "start_date": "2026-06-01",
    "end_date": "2026-10-18",
    "link": "https://english.shanghai.gov.cn/en-ArtExhibitions/20260710/093ebf7888d04eedbe1428e0fcf7aa3f.html",
    "description": "上海图书馆东馆举办的大英图书馆猫展，展出大英图书馆馆藏的珍稀文献、手稿和插图复制品，追溯猫与人类文明同行的旅程。探讨猫在不同文化中的角色，从古埃及的神圣地位到奥斯曼帝国的珍爱伙伴。展示达芬奇、肖邦等大师作品及巴尔扎克、海明威、牛顿等著名爱猫人的故事。",
    "fee": "收费（大麦购票）",
    "source": "Shanghai Municipal Administration of Culture and Tourism",
    "family_friendly": true
  },
  {
    "title": "2026全国青少年心理成长知识与应用创新大赛上海赛区",
    "venue": "金山体育馆综合馆",
    "city": "shanghai",
    "start_date": "2026-07-18",
    "end_date": "2026-07-19",
    "link": "http://m.toutiao.com/group/7662947664883696134/",
    "description": "教育部2025-2028学年面向中小学生的全国性竞赛活动名单中的自然科学素养类赛事。设三大独立赛项：五育并举促进学生心理健康知识普及、趣味心理运动会、小小心理学家创新大赛。参赛选手凭参赛证可免费游金山城市沙滩、花开海上生态园。",
    "fee": "免费（公益办赛）",
    "source": "金山区体育局",
    "family_friendly": true
  },
  {
    "title": "十八斗半日研学营",
    "venue": "金山十八斗",
    "city": "shanghai",
    "start_date": "2026-07-16",
    "end_date": "2026-08-31",
    "link": "http://m.toutiao.com/group/7662947664883696134/",
    "description": "传统建筑文化课程研学，199元/户（一大一小），小朋友单独制作。满15组家庭方可计为团队订单，未满不成团。需在2026年7月16日之前完成预订。",
    "fee": "收费（199元/户）",
    "source": "金山区体育局",
    "family_friendly": true
  },
  {
    "title": "上美影泡泡米·国漫美育成长季",
    "venue": "上海多个文化场馆",
    "city": "shanghai",
    "start_date": "2026-07-08",
    "end_date": "2026-08-31",
    "link": "https://www.meet-in-shanghai.net/cn/news/the-2026-shanghai-tourism-festival-summer-tourism-season-kicks-off-on-july-8-170-activities-and-six-major-themed-weeks-are-online-388024/",
    "description": "以上美影经典动画IP为核心，开设国漫手作、西游研学、光影剧场、非遗美育课堂，沉浸式感受东方美学。作为上海旅游节暑期旅游季艺彩申城主题板块活动之一。",
    "fee": "收费",
    "source": "乐游上海",
    "family_friendly": true
  },
  {
    "title": "2026上海旅游节·一城精彩·文明奇遇文旅联票活动",
    "venue": "上海全市20余家文博场馆与文旅地标",
    "city": "shanghai",
    "start_date": "2026-07-08",
    "end_date": "2026-10-06",
    "link": "https://www.meet-in-shanghai.net/cn/news/the-2026-shanghai-tourism-festival-summer-tourism-season-kicks-off-on-july-8-170-activities-and-six-major-themed-weeks-are-online-388024/",
    "description": "2026上海旅游节暑期重磅上线文博主题联票活动，覆盖海上萌宠、文博非遗、节气烟火等档期，联动上海博物馆美洲古文明大展等资源，整合文博展馆与文旅点位，一票畅玩沉浸式感受海派文脉与非遗文化。联票于7月8日在沪小游小程序正式发售。",
    "fee": "收费（联票）",
    "source": "乐游上海",
    "family_friendly": true
  },
  {
    "title": "西岸凤巢HeyBlue Oasis水上乐园",
    "venue": "西岸凤巢大师公园",
    "city": "shanghai",
    "start_date": "2026-06-20",
    "end_date": "2026-08-31",
    "link": "http://m.toutiao.com/group/7663419363839509019/",
    "description": "坐落于大师公园内，整片戏水区域配备多样水上互动设施，大片泳池适配全年龄段玩水，带娃消暑轻松省心，实现不费妈遛娃。乐园紧邻两大露天影院，玩水结束可直接观影。",
    "fee": "收费",
    "source": "新民晚报",
    "family_friendly": true
  },
  {
    "title": "GATE M水岸露天电影节",
    "venue": "西岸梦中心",
    "city": "shanghai",
    "start_date": "2026-07-02",
    "end_date": "2026-07-20",
    "link": "http://m.toutiao.com/group/7663419363839509019/",
    "description": "打造四大观影场地：西岸梦中心水岸剧场以黄浦江晚霞为天然幕布；西岸梦中心落日剧场依托滑板公园无需预约；西岸凤巢森林影院在水上乐园旁；西岸凤巢星光影院在B1下沉广场。三十余部动画、经典、科幻影片循环放映。",
    "fee": "免费（水岸剧场需线上预约，其余随到随坐）",
    "source": "新民晚报",
    "family_friendly": true
  },
  {
    "title": "迪士尼米奇妙妙之旅快闪",
    "venue": "西岸滨江船坞区域",
    "city": "shanghai",
    "start_date": "2026-06-18",
    "end_date": "2026-08-02",
    "link": "http://m.toutiao.com/group/7663419363839509019/",
    "description": "藏在滨江船坞区域，是年轻人与亲子出游必打卡点位。八米高飞行员米奇巨型气模十分出片，米妮、唐老鸭雕塑散落场地，复古大头贴、限定文创随心挑选。周末开通主题观光巴士，串联滨江各大景点。",
    "fee": "免费",
    "source": "新民晚报",
    "family_friendly": true
  },
  {
    "title": "2026上海湾区·金山城市沙滩音乐啤酒微醺夜",
    "venue": "金山城市沙滩",
    "city": "shanghai",
    "start_date": "2026-07-18",
    "end_date": "2026-07-26",
    "link": "https://www.shanghai.gov.cn/nw17239/20260622/ca85991680884f8f89f6efc86da449f3.html",
    "description": "7月18-19日、25-26日（周末）开展，海风伴音浪，微醺享夏夜。小型现场演出轮番登场，打造轻松惬意的海边狂欢派对。",
    "fee": "收费（沙滩门票）",
    "source": "上海市人民政府",
    "family_friendly": true
  },
  {
    "title": "葫芦兄弟葫闹派对IP快闪",
    "venue": "南京路步行街",
    "city": "shanghai",
    "start_date": "2026-07-08",
    "end_date": "2026-08-31",
    "link": "https://whlyj.sh.gov.cn/wlyw/20260702/2dbbdd4047684d548deff8720480fd2f.html",
    "description": "南京路步行街葫闹派对联动葫芦兄弟IP打造艺术装置与快闪体验，梧桐深处文旅融合活动。",
    "fee": "免费",
    "source": "上海市文化和旅游局",
    "family_friendly": true
  },
  {
    "title": "苏河乘风凉夏季主题航班",
    "venue": "苏州河",
    "city": "shanghai",
    "start_date": "2026-07-08",
    "end_date": "2026-08-31",
    "link": "https://whlyj.sh.gov.cn/wlyw/20260702/2dbbdd4047684d548deff8720480fd2f.html",
    "description": "苏州河上苏河乘风凉夏季主题航班推出萌宠游船、星空晚宴、音乐Live、雅韵茶旅四大特色航线。",
    "fee": "收费",
    "source": "上海市文化和旅游局",
    "family_friendly": true
  },
  {
    "title": "上海城市草坪音乐会夏之魅",
    "venue": "黄浦江畔",
    "city": "shanghai",
    "start_date": "2026-07-08",
    "end_date": "2026-08-31",
    "link": "https://whlyj.sh.gov.cn/wlyw/20260702/2dbbdd4047684d548deff8720480fd2f.html",
    "description": "上海城市草坪音乐会夏之魅连演7场，演艺大世界天天有戏演艺市集将在南京东路六合路集中呈现。",
    "fee": "免费",
    "source": "上海市文化和旅游局",
    "family_friendly": true
  },
  {
    "title": "徐家汇体育公园乒乓球亲子实战",
    "venue": "徐家汇体育公园综合馆乒乓球馆",
    "city": "shanghai",
    "start_date": "2026-07-01",
    "end_date": "2026-08-31",
    "link": "http://m.toutiao.com/group/7662955572609696292/",
    "description": "来到徐家汇体育公园综合馆乒乓球馆，不仅是大众乐园，更是国球荣光的传承地。为孩子预约一节基础体验课，或亲自上阵来一场亲子对决。",
    "fee": "收费",
    "source": "上海体育",
    "family_friendly": true
  },
  {
    "title": "上海夏季音乐节梦想舞台学生艺术团及联盟专场演出",
    "venue": "捷豹上海交响音乐厅",
    "city": "shanghai",
    "start_date": "2026-07-13",
    "end_date": "2026-07-20",
    "link": "http://edu.sh.gov.cn/web/detail_jyzc/25600cda-fa4f-4cc3-b97f-23b7dd15d7f7",
    "description": "演出汇聚上海学生民族乐团、交响乐团、合唱团及联盟校乐团的千余名青少年，在捷豹上海交响音乐厅呈现9台精彩演出。融合红色基因传承、区域美育协同、原创艺术表达三大核心亮点。7月13日、14日和20日，通过上海艺教、上海文教结合、上海交响乐团等视频号播出。",
    "fee": "免费（无需报名）",
    "source": "上海市教育委员会",
    "family_friendly": true
  },
  {
    "title": "2026年上海国际青少年科技创新挑战营暨明日科技之星国际邀请赛",
    "venue": "上海市徐汇区青少年STEM教育实践体验中心",
    "city": "shanghai",
    "start_date": "2026-07-21",
    "end_date": "2026-07-26",
    "link": "http://edu.sh.gov.cn/web/detail_jyzc/25600cda-fa4f-4cc3-b97f-23b7dd15d7f7",
    "description": "主体内容包含交流和竞赛两大板块，交流板块包括青少年科技创新成果展示和路演、科技教育资源嘉年华、云端展示、Vlog创意行动、文化交流和人工智能项目互动体验等，竞赛板块包括明日科技之星国际邀请赛、科学辩论团体邀请赛等。2008-2013年间出生的全日制在校中学生可在官网报名。",
    "fee": "免费（报名参与）",
    "source": "上海市教育委员会",
    "family_friendly": true
  },
  {
    "title": "周周播素质教育校外名师直播课堂",
    "venue": "上海市科技艺术教育中心（线上）",
    "city": "shanghai",
    "start_date": "2026-07-01",
    "end_date": "2026-08-31",
    "link": "http://edu.sh.gov.cn/web/detail_jyzc/25600cda-fa4f-4cc3-b97f-23b7dd15d7f7",
    "description": "周周播素质教育直播课堂每周六下午15:00-16:00准时开播。课堂邀请各领域名家名师线上授课，打造直播间主题、城市行走、场馆实景等特色课程系列，内容涵盖艺术人文、体育健康、科技劳动、自然生态等。",
    "fee": "免费",
    "source": "上海市教育委员会",
    "family_friendly": true
  },
  {
    "title": "2026年宝山区图书馆儿童文学创作大赛及名家分享",
    "venue": "宝山区图书馆",
    "city": "shanghai",
    "start_date": "2026-07-01",
    "end_date": "2026-08-31",
    "link": "http://m.toutiao.com/group/7663442840953618950/",
    "description": "7月至8月，宝山区图书馆邀请儿童文学名家线下分享并推出儿童文学创作大赛，挖掘青少年写作潜力。联动区内文化场馆，开展研学与实践，科普工坊、非遗手工坊、经典文学讲座、亲子绘本故事会轮番上线。",
    "fee": "免费",
    "source": "新民晚报",
    "family_friendly": true
  },
  {
    "title": "杨浦区图书馆侦探逻辑专题",
    "venue": "杨浦区图书馆",
    "city": "shanghai",
    "start_date": "2026-08-25",
    "end_date": "2026-08-31",
    "link": "http://m.toutiao.com/group/7663442840953618950/",
    "description": "邀请推理作家、文史学者面对面交流，8月底专门开设侦探逻辑专题，锻炼青少年思辨和写作的能力。",
    "fee": "免费",
    "source": "新民晚报",
    "family_friendly": true
  }
]
