[
  {
    "title": "寻绎夏商——夏商时期长江流域文明特展",
    "venue": "盘龙城遗址博物院",
    "city": "wuhan",
    "start_date": "2026-06-13",
    "end_date": "2026-10-18",
    "link": "http://www.hb.chinanews.com.cn/news/2026/0612/430076.html",
    "description": "全国35家重量级文博单位联合参展，163件夏商珍贵文物集中亮相，包括华夏第一鼎网格纹铜鼎、三星堆青铜面具、商代玉戈之王等国宝，展现夏商时期长江流域文明风貌。",
    "fee": "免费需预约",
    "source": "盘龙城遗址博物院",
    "family_friendly": true
  },
  {
    "title": "盘龙城考古体验区模拟挖宝亲子活动",
    "venue": "盘龙城遗址博物院考古体验区",
    "city": "wuhan",
    "start_date": "2026-07-01",
    "end_date": "2026-08-31",
    "link": "http://m.toutiao.com/group/7654856685957169673/",
    "description": "考古木屋体验区开设考古体验课、制陶工坊，小朋友亲手体验考古工作，模拟挖宝、手工制陶，沉浸式感受3500年前商代先民生活。",
    "fee": "收费",
    "source": "盘龙城遗址博物院",
    "family_friendly": true
  },
  {
    "title": "湖北考古博物馆青铜文化亲子研学营",
    "venue": "湖北考古博物馆",
    "city": "wuhan",
    "start_date": "2026-07-01",
    "end_date": "2026-08-31",
    "link": "http://m.toutiao.com/group/7650458581792080427/",
    "description": "面向8-12岁青少年的亲子研学营，观看青铜文化影片、参观主题展览、聆听考古专家讲解铸铜工艺，动手用黏土复刻青铜器，寓教于乐普及考古知识。",
    "fee": "收费",
    "source": "湖北考古博物馆",
    "family_friendly": true
  },
  {
    "title": "黄陂区博物馆NFC文物拾珍互动打卡活动",
    "venue": "黄陂区博物馆",
    "city": "wuhan",
    "start_date": "2026-06-13",
    "end_date": "2026-12-30",
    "link": "http://m.toutiao.com/group/7650458581792080427/",
    "description": "线下完成6处点位打卡，集齐印章可兑换木兰系列文创，馆内同步上线AI智能讲解，游客可随时互动提问，借助数字科技读懂馆藏文物。",
    "fee": "免费",
    "source": "黄陂区博物馆",
    "family_friendly": true
  },
  {
    "title": "湖北明清古建筑博物馆榫卯营造技艺科普活动",
    "venue": "湖北明清古建筑博物馆",
    "city": "wuhan",
    "start_date": "2026-07-01",
    "end_date": "2026-08-31",
    "link": "http://m.toutiao.com/group/7650458581792080427/",
    "description": "全面开放古建群落，配备专业讲解，介绍榫卯、砖雕、木雕等传统营造技艺，解读明清荆楚建筑风格与民俗文化，开展古建保护科普。",
    "fee": "免费",
    "source": "湖北明清古建筑博物馆",
    "family_friendly": true
  },
  {
    "title": "武汉自然博物馆八周年主题活动",
    "venue": "武汉自然博物馆",
    "city": "wuhan",
    "start_date": "2026-07-18",
    "end_date": "2026-08-31",
    "link": "http://m.toutiao.com/group/7663320941941785138/",
    "description": "八周年馆庆系列活动，小小志愿者上岗讲解、限定套色馆章兑换、十大镇馆之宝打卡拍照，还有大河少年说科普视频线上展播。",
    "fee": "免费（需园博园门票）",
    "source": "武汉自然博物馆",
    "family_friendly": true
  },
  {
    "title": "小小探险家——武汉自然博物馆沉浸式剧游",
    "venue": "武汉自然博物馆",
    "city": "wuhan",
    "start_date": "2026-07-01",
    "end_date": "2026-08-31",
    "link": "https://m.weibo.cn/detail/5320913085273553",
    "description": "8位趣味NPC在线带队闯关，沉浸式逛展厅解锁自然知识，14:00-17:00活动时段，避暑研学遛娃一站式搞定。",
    "fee": "收费",
    "source": "武汉市文化和旅游局",
    "family_friendly": true
  },
  {
    "title": "八七会议会址纪念馆暑期延时开放",
    "venue": "八七会议会址纪念馆",
    "city": "wuhan",
    "start_date": "2026-07-14",
    "end_date": "2026-08-31",
    "link": "http://www.192787.cn/view/690.html",
    "description": "暑期延长开放至18:30（17:30停止入馆），每周五闭馆（法定节假日除外），可通过官方公众号预约入馆参观，接受红色教育。",
    "fee": "免费需预约",
    "source": "八七会议会址纪念馆",
    "family_friendly": true
  },
  {
    "title": "八七红小小宣讲员红色讲解活动",
    "venue": "八七会议会址纪念馆",
    "city": "wuhan",
    "start_date": "2026-07-01",
    "end_date": "2026-08-31",
    "link": "https://m.sohu.com/a/1044347266_121107011/",
    "description": "身着统一服装的小小宣讲员穿梭于展厅，用稚嫩真挚的童声为观众讲述革命先辈英勇事迹与文物背后的红色故事。",
    "fee": "免费",
    "source": "八七会议会址纪念馆",
    "family_friendly": true
  },
  {
    "title": "八七红共享思政课《红旗漫卷大别山》",
    "venue": "八七会议会址纪念馆",
    "city": "wuhan",
    "start_date": "2026-07-01",
    "end_date": "2026-08-31",
    "link": "https://m.sohu.com/a/1044651160_121106908/",
    "description": "联合武汉市青少年宫打造的共享思政课，通过角色扮演、同心齐唱、互动游戏等形式，带领学生重温大别山革命斗争峥嵘岁月。",
    "fee": "免费",
    "source": "八七会议会址纪念馆/武汉市青少年宫",
    "family_friendly": true
  },
  {
    "title": "走读民间文学——武汉大禹治水传说研学活动",
    "venue": "晴川阁武汉大禹文化博物馆",
    "city": "wuhan",
    "start_date": "2026-07-01",
    "end_date": "2026-08-31",
    "link": "http://m.toutiao.com/group/7651198573154501160/",
    "description": "参观大禹治水遗址遗迹，观看实景木偶剧，欣赏大禹神话园精美雕像，以听看触思讲的形式沉浸式学习武汉大禹治水传说。",
    "fee": "免费",
    "source": "武汉大禹文化博物馆",
    "family_friendly": true
  },
  {
    "title": "大禹晴川情实景木偶剧展演",
    "venue": "晴川阁武汉大禹文化博物馆",
    "city": "wuhan",
    "start_date": "2026-07-01",
    "end_date": "2026-08-31",
    "link": "http://m.toutiao.com/group/7651198573154501160/",
    "description": "与武汉人民艺术剧院联合推出的非遗项目创新展演，融合武汉大禹治水传说与武汉杖头木偶戏两大国家级非遗项目。",
    "fee": "收费",
    "source": "武汉大禹文化博物馆/武汉人艺",
    "family_friendly": true
  },
  {
    "title": "晴川禹声——小小非遗传承人志愿讲解",
    "venue": "晴川阁武汉大禹文化博物馆",
    "city": "wuhan",
    "start_date": "2026-07-01",
    "end_date": "2026-08-31",
    "link": "http://m.toutiao.com/group/7651198573154501160/",
    "description": "小小非遗传承人为游客讲解重点古建筑，展示学习成果，为非遗传承注入新鲜血液，青少年可报名参与志愿者培训。",
    "fee": "免费",
    "source": "武汉大禹文化博物馆",
    "family_friendly": true
  },
  {
    "title": "气蕴华夏 象动楚天——中国气象事业历程展",
    "venue": "晴川阁武汉大禹文化博物馆主楼",
    "city": "wuhan",
    "start_date": "2026-03-23",
    "end_date": "2026-08-23",
    "link": "http://m.toutiao.com/group/7641917554684690959/",
    "description": "系统梳理我国气象事业从古代观象授时、节气历法，到近现代科学观测、技术革新，再到现代化气象体系建设的完整脉络。",
    "fee": "免费",
    "source": "武汉大禹文化博物馆",
    "family_friendly": true
  },
  {
    "title": "湖北省科技馆趣玩一夏科学同行暑期主题科普活动",
    "venue": "湖北省科技馆",
    "city": "wuhan",
    "start_date": "2026-07-01",
    "end_date": "2026-08-31",
    "link": "http://m.toutiao.com/group/7662255602755781162/",
    "description": "面向4-15岁青少年及亲子家庭，特色研学活动、趣味科学课堂、前沿科技互动体验一站式解锁，含精品科学课程、AI创意编程、亲子科学运动会。",
    "fee": "免费需预约",
    "source": "湖北省科技馆",
    "family_friendly": true
  },
  {
    "title": "未来科学节-机器人嘉年华",
    "venue": "湖北省科技馆一楼大厅",
    "city": "wuhan",
    "start_date": "2026-07-19",
    "end_date": "2026-07-19",
    "link": "https://www.hbstm.org.cn/webart/WebArtInfo/3636/?p=72",
    "description": "智慧积木机器人体验项目、机器人大擂台，亲子家庭共同参与，感受前沿机器人科技魅力。",
    "fee": "免费需预约",
    "source": "湖北省科技馆",
    "family_friendly": true
  },
  {
    "title": "科技馆小达人夏令营——4天解锁3大国家级实验室",
    "venue": "湖北省科技馆",
    "city": "wuhan",
    "start_date": "2026-07-15",
    "end_date": "2026-08-31",
    "link": "https://m.sohu.com/a/1050411715_121106908/",
    "description": "4天时间走进武汉大学、华中师范大学、武汉科技大学等3所高校国家级重点实验室，深度玩转8大主题展厅，动手做实验看炫酷科学秀。",
    "fee": "收费",
    "source": "湖北省科技馆",
    "family_friendly": true
  },
  {
    "title": "机器人总动员周末仿生机器人表演",
    "venue": "湖北省科技馆",
    "city": "wuhan",
    "start_date": "2026-07-01",
    "end_date": "2026-08-31",
    "link": "http://m.toutiao.com/group/7662255602755781162/",
    "description": "每周末上演仿生机器狗特技表演、遥控机甲战车对战、六足仿生机器人巡游，零距离感受前沿机器人科技魅力。",
    "fee": "免费需预约",
    "source": "湖北省科技馆",
    "family_friendly": true
  },
  {
    "title": "湖北省科技馆4D特效影院暑期放映",
    "venue": "湖北省科技馆",
    "city": "wuhan",
    "start_date": "2026-07-01",
    "end_date": "2026-08-31",
    "link": "http://m.toutiao.com/group/7662255602755781162/",
    "description": "4D影院《海龟之旅》《地心游记》《变形计》《巨兽》，飞翔影院《遇见青海》《海底总动员》，前往总服务台免费领取观影票。",
    "fee": "免费需预约",
    "source": "湖北省科技馆",
    "family_friendly": true
  },
  {
    "title": "童趣有氧 骑趣东湖骑行研学营",
    "venue": "东湖绿道楚风园湖光序曲广场",
    "city": "wuhan",
    "start_date": "2026-07-01",
    "end_date": "2026-08-31",
    "link": "http://m.toutiao.com/group/7647733561180668454/",
    "description": "专业骑行教练带教，学习单车理论和骑行技巧，趣味battle赛绕桩慢骑接力，捷安特专业用车，1:5高配比导师全程安全保障。",
    "fee": "收费",
    "source": "东湖文旅",
    "family_friendly": true
  },
  {
    "title": "东湖帆船夏令营——中帆协认证小水手培训",
    "venue": "东湖帆船公园",
    "city": "wuhan",
    "start_date": "2026-06-22",
    "end_date": "2026-08-28",
    "link": "http://m.toutiao.com/group/7647733561180668454/",
    "description": "5天4夜零基础起步，中帆协认证培训中心，16小时水上训练穿插造船工程、CPR急救认证、游艇跳岛等，结业获国家一级小水手证书。",
    "fee": "收费",
    "source": "东湖帆船公园",
    "family_friendly": true
  },
  {
    "title": "东湖沙滩螃蟹部落亲子抓蟹体验",
    "venue": "东湖沙滩景区",
    "city": "wuhan",
    "start_date": "2026-07-01",
    "end_date": "2026-08-31",
    "link": "https://ctdsbepaper.hubeidaily.net/pad/content/202607/15/content_353304.html",
    "description": "99元通玩两大区域七大项目，螃蟹部落每日投放约1000只螃蟹，孩子们提小桶抓螃蟹，沙滩淘宝、沙堡工坊、沙滩卡丁车等丰富项目。",
    "fee": "收费",
    "source": "东湖沙滩景区",
    "family_friendly": true
  },
  {
    "title": "东湖荷园荷花展——千亩荷塘夏日限定",
    "venue": "东湖荷园",
    "city": "wuhan",
    "start_date": "2026-06-10",
    "end_date": "2026-08-31",
    "link": "https://ctdsbepaper.hubeidaily.net/pad/content/202607/15/content_353304.html",
    "description": "1200余种荷花占全国品种90%以上，珍稀品种达500余个，全新引进60个荷花新品种、80个睡莲新品种，克鲁兹王莲巨型莲叶标志性景观。",
    "fee": "免费",
    "source": "东湖风景区",
    "family_friendly": true
  },
  {
    "title": "木兰草原国风天水节——水火对话国风狂欢",
    "venue": "木兰草原景区",
    "city": "wuhan",
    "start_date": "2026-06-27",
    "end_date": "2026-08-31",
    "link": "https://www.wuhan.gov.cn/zjwh/whly/202606/t20260629_2814640.shtml",
    "description": "白天浪浪谷水乐园、高空玻璃漂流、激流勇进、水上卡丁船，夜间沉浸式国风夜游盛典，圣火鼓舞飞天祈福水火交融五大篇章串联。",
    "fee": "收费",
    "source": "木兰草原景区",
    "family_friendly": true
  },
  {
    "title": "木兰草原侏罗纪主题玻璃漂流",
    "venue": "木兰草原景区",
    "city": "wuhan",
    "start_date": "2026-07-01",
    "end_date": "2026-08-31",
    "link": "http://m.toutiao.com/group/7658228015800877620/",
    "description": "全长2160米的水上过山车，最高落差百米，滑道沿途装扮成侏罗纪公园，设置恐龙主题互动装置，身处恐龙世界乐趣十足。",
    "fee": "收费",
    "source": "木兰草原景区",
    "family_friendly": true
  },
  {
    "title": "木兰天池峡谷玻璃漂流",
    "venue": "木兰天池景区",
    "city": "wuhan",
    "start_date": "2026-07-01",
    "end_date": "2026-08-31",
    "link": "http://m.toutiao.com/group/7658228015800877620/",
    "description": "玻璃漂流滑道全长2000米，超百米高低落差，九曲十八弯360度回转造型，七彩花道段浪漫好看，穿行峡谷森林之中。",
    "fee": "收费",
    "source": "木兰天池景区",
    "family_friendly": true
  },
  {
    "title": "木兰云雾山陂西峡森林漂流",
    "venue": "木兰云雾山景区",
    "city": "wuhan",
    "start_date": "2026-07-01",
    "end_date": "2026-08-31",
    "link": "http://m.toutiao.com/group/7658228015800877620/",
    "description": "5公里河道160米总落差，80%河道藏在密林隧道里几乎无日晒，急弯冲浪平缓浅滩打水仗，今夏推出夜漂体验。",
    "fee": "收费",
    "source": "木兰云雾山景区",
    "family_friendly": true
  },
  {
    "title": "锦里沟土家泼水节暨神牛溪峡谷漂流",
    "venue": "锦里沟景区（木兰神牛溪）",
    "city": "wuhan",
    "start_date": "2026-06-19",
    "end_date": "2026-08-31",
    "link": "https://whwb.cjn.cn/h5/html5/2026-06/17/content_48088_3543099.htm",
    "description": "前半段高空玻璃滑道俯冲后半段原生态森林峡谷河道，全长4.8公里垂直落差220米，漂流结束衔接土家泼水广场一站式玩水。",
    "fee": "收费",
    "source": "锦里沟景区",
    "family_friendly": true
  },
  {
    "title": "清凉寨悬崖高空玻璃漂流",
    "venue": "木兰清凉寨景区",
    "city": "wuhan",
    "start_date": "2026-07-01",
    "end_date": "2026-08-31",
    "link": "http://m.toutiao.com/group/7658228015800877620/",
    "description": "全长3.6公里落差136米相当于45层高楼直冲而下，玻璃加漂流混搭刺激翻倍，全程穿行丛林360度无边际视野。",
    "fee": "收费",
    "source": "木兰清凉寨景区",
    "family_friendly": true
  },
  {
    "title": "野村谷亲子浪浪漂与花溪谷漂流",
    "venue": "野村谷景区",
    "city": "wuhan",
    "start_date": "2026-07-01",
    "end_date": "2026-08-31",
    "link": "http://m.toutiao.com/group/7658228015800877620/",
    "description": "双漂上线，1.2公里浪浪漂平缓安全老少皆宜，3公里花溪谷漂蜿蜒穿行花海移步换景，全线安全员护航头盔救生衣免费。",
    "fee": "收费",
    "source": "野村谷景区",
    "family_friendly": true
  },
  {
    "title": "木兰花乡荧光旋转玻璃漂流",
    "venue": "木兰花乡景区",
    "city": "wuhan",
    "start_date": "2026-07-01",
    "end_date": "2026-08-31",
    "link": "http://m.toutiao.com/group/7658228015800877620/",
    "description": "玻璃天桥加玻璃漂流双重体验，668米螺旋形旋转玻璃漂流加308米荧光洞漂流，飞天遁地般的漂流体验。",
    "fee": "收费",
    "source": "木兰花乡景区",
    "family_friendly": true
  },
  {
    "title": "伦敦西区原版音乐剧《玛蒂尔达》十五周年国际巡演武汉站",
    "venue": "武汉琴台大剧院",
    "city": "wuhan",
    "start_date": "2026-07-10",
    "end_date": "2026-07-19",
    "link": "https://news.hubeidaily.net/mobile/c_5081682.html",
    "description": "英国皇家莎士比亚剧团打造的经典音乐剧，13场驻场演出，讲述聪明小女孩玛蒂尔达用智慧和勇气改写命运的故事，全龄适配佳作。",
    "fee": "收费",
    "source": "武汉琴台大剧院",
    "family_friendly": true
  },
  {
    "title": "不怕大灰狼——音乐启蒙动画音乐会",
    "venue": "武汉琴台音乐厅",
    "city": "wuhan",
    "start_date": "2026-08-18",
    "end_date": "2026-08-18",
    "link": "https://www.xinruipiao.com/ertongqinzi/29661.html",
    "description": "融合多国优秀动画片片段，现场演奏印度风琴、玩具钢琴、泰勒明电子琴等奇妙乐器，音乐启蒙与童趣故事完美结合。",
    "fee": "收费",
    "source": "琴台音乐厅",
    "family_friendly": true
  },
  {
    "title": "英国BBC正版授权亲子舞台剧《布鲁伊的大宝藏》",
    "venue": "湖北剧院",
    "city": "wuhan",
    "start_date": "2026-07-26",
    "end_date": "2026-07-26",
    "link": "http://m.toutiao.com/group/7657843230155604520/",
    "description": "超人气动画IP布鲁伊首次登陆武汉，互动式亲子舞台剧，一家四口温馨冒险故事，四场连演覆盖全天不同时段。",
    "fee": "收费",
    "source": "湖北剧院",
    "family_friendly": true
  },
  {
    "title": "长江人艺儿童剧《小火神的大麻烦》",
    "venue": "湖北剧院",
    "city": "wuhan",
    "start_date": "2026-07-04",
    "end_date": "2026-07-04",
    "link": "http://m.toutiao.com/group/7657843230155604520/",
    "description": "长江人民艺术剧院原创儿童剧，适合小朋友观看的奇幻故事，寓教于乐传递安全知识与成长道理。",
    "fee": "收费",
    "source": "湖北剧院",
    "family_friendly": true
  },
  {
    "title": "欢乐童年奇幻成长冒险儿童剧《匹诺曹成长记》",
    "venue": "湖北剧院小剧场",
    "city": "wuhan",
    "start_date": "2026-07-05",
    "end_date": "2026-07-05",
    "link": "http://m.toutiao.com/group/7657843230155604520/",
    "description": "经典童话匹诺曹的改编儿童剧，木偶男孩的成长冒险故事，教导孩子诚实勇敢的珍贵品质。",
    "fee": "收费",
    "source": "湖北剧院",
    "family_friendly": true
  },
  {
    "title": "欢乐童年非遗国粹亲子皮影戏",
    "venue": "湖北剧院小剧场",
    "city": "wuhan",
    "start_date": "2026-07-18",
    "end_date": "2026-07-18",
    "link": "http://m.toutiao.com/group/7657843230155604520/",
    "description": "传统非遗皮影戏演出，亲子共同感受传统民间艺术魅力，精彩剧目配合现场互动。",
    "fee": "收费",
    "source": "湖北剧院",
    "family_friendly": true
  },
  {
    "title": "国潮沉浸式儿童剧《西游记之大闹天宫》",
    "venue": "湖北剧院小剧场",
    "city": "wuhan",
    "start_date": "2026-07-19",
    "end_date": "2026-07-19",
    "link": "http://m.toutiao.com/group/7657843230155604520/",
    "description": "国潮风格演绎经典西游记故事，美猴王大闹天宫的传奇经历，沉浸式舞台体验。",
    "fee": "收费",
    "source": "湖北剧院",
    "family_friendly": true
  },
  {
    "title": "大型异域魔幻儿童音乐剧《阿拉丁神灯》",
    "venue": "湖北剧院小剧场",
    "city": "wuhan",
    "start_date": "2026-07-25",
    "end_date": "2026-07-25",
    "link": "http://m.toutiao.com/group/7657843230155604520/",
    "description": "经典阿拉伯童话改编的儿童音乐剧，神奇的魔法灯、异域风情歌舞，带来充满想象力的视听体验。",
    "fee": "收费",
    "source": "湖北剧院",
    "family_friendly": true
  },
  {
    "title": "奇幻科普儿童剧《闹闹与精灵》",
    "venue": "湖北剧院小剧场",
    "city": "wuhan",
    "start_date": "2026-07-25",
    "end_date": "2026-07-26",
    "link": "http://m.toutiao.com/group/7657843230155604520/",
    "description": "长江人艺出品的奇幻科普儿童剧，将科学知识融入奇幻冒险故事，边看剧边学生物知识。",
    "fee": "收费",
    "source": "湖北剧院",
    "family_friendly": true
  },
  {
    "title": "木偶剧《卡卡的神奇药水》",
    "venue": "武汉人艺中南剧场木偶剧场",
    "city": "wuhan",
    "start_date": "2026-07-18",
    "end_date": "2026-07-18",
    "link": "http://m.toutiao.com/group/7662291843161293363/",
    "description": "2026暑期儿童戏剧周剧目，杖头木偶剧新作品，保有童真与趣味，儿童视角讲述奇幻成长故事。",
    "fee": "收费",
    "source": "武汉人民艺术剧院",
    "family_friendly": true
  },
  {
    "title": "儿童歌舞剧《彩虹城堡》",
    "venue": "临空港大剧院",
    "city": "wuhan",
    "start_date": "2026-07-14",
    "end_date": "2026-07-14",
    "link": "https://m.hbtv.com.cn/p/4617778.html",
    "description": "英国剧团带来的儿童歌舞剧，通过互动舞蹈游戏等形式让孩子在快乐中学习英语，20元惠民票价。",
    "fee": "收费",
    "source": "临空港大剧院",
    "family_friendly": true
  },
  {
    "title": "洪孩子暑期阅读游园会",
    "venue": "洪山区图书馆",
    "city": "wuhan",
    "start_date": "2026-07-01",
    "end_date": "2026-08-31",
    "link": "http://hbwh.wenming.cn/zt2026/2026sqjzxd/2026qwyx/202607/t20260707_9292090.html",
    "description": "创新打造游园打卡加沉浸式体验模式，五大特色互动区：国风体验区、数字科普VR区、诗词传递、数独挑战、书籍漂流时光邮局。",
    "fee": "免费",
    "source": "洪山区图书馆",
    "family_friendly": true
  },
  {
    "title": "第41届马良杯少年儿童书画展示活动",
    "venue": "全市各区图书馆",
    "city": "wuhan",
    "start_date": "2026-05-29",
    "end_date": "2026-10-31",
    "link": "http://m.toutiao.com/group/7657549578228531753/",
    "description": "武汉市知识工程少儿读书系列活动重要组成，分绘画和书法两大类，5至15周岁少年儿童可参与，10月举办优秀成果巡展。",
    "fee": "免费",
    "source": "武汉市少年儿童图书馆",
    "family_friendly": true
  },
  {
    "title": "武昌区第十四届社区亲子读书季",
    "venue": "武昌区各街道社区",
    "city": "wuhan",
    "start_date": "2026-07-03",
    "end_date": "2026-08-31",
    "link": "http://hbwh.wenming.cn/rdjj/202607/t20260706_9289830.html",
    "description": "50余个阅读空间54场文明实践活动，翻书闯长征红色阅读擂台、AI带你读武昌魔法训练营、汉腔萌娃方言故事会、作家面对面写作训练营。",
    "fee": "免费",
    "source": "武昌区文旅局",
    "family_friendly": true
  },
  {
    "title": "湖北省少年儿童图书馆第五十期小小图书管理员",
    "venue": "湖北省少年儿童图书馆",
    "city": "wuhan",
    "start_date": "2026-07-24",
    "end_date": "2026-08-31",
    "link": "http://m.toutiao.com/group/7660424181980430858/",
    "description": "7至16岁热爱阅读的小读者可报名，理论学习加上岗实践，参与图书整理上架、引导借阅、协助活动等，完成者获社会实践证书。",
    "fee": "免费需报名",
    "source": "湖北省少年儿童图书馆",
    "family_friendly": true
  },
  {
    "title": "江岸区非遗亲子游文化伴成长线路",
    "venue": "江岸区汉口历史风貌区",
    "city": "wuhan",
    "start_date": "2026-07-01",
    "end_date": "2026-08-31",
    "link": "http://www.ctnews.com.cn/wenhua/content/2026-07/02/content_189235.html",
    "description": "串联吉庆民俗街、群众艺术馆民俗展厅、汉剧博物馆、木偶剧场等点位，剪纸面塑楚香互动体验，杖头木偶戏汉剧展演。",
    "fee": "免费",
    "source": "江岸区文旅局",
    "family_friendly": true
  },
  {
    "title": "江城文驿汇200场公益文艺活动",
    "venue": "全市20家文化驿站",
    "city": "wuhan",
    "start_date": "2026-06-28",
    "end_date": "2026-09-20",
    "link": "https://m.sohu.com/a/1042651403_121106908/",
    "description": "全市20座特色文化驿站同步联动，戏曲非遗传承、艺术普及培训、亲子手工体验、文化沙龙讲座等200场公益活动全部免费。",
    "fee": "免费",
    "source": "武汉市群众艺术馆",
    "family_friendly": true
  },
  {
    "title": "湖北省体育局崇仁夏令营",
    "venue": "湖北省体育局崇仁中心",
    "city": "wuhan",
    "start_date": "2026-06-28",
    "end_date": "2026-08-31",
    "link": "http://tyj.hubei.gov.cn/bmdt/zhxx/202606/t20260630_5967244.shtml",
    "description": "涵盖游泳、体适能快乐体操、羽毛球、乒乓球、网球、篮球、排球、足球、射击、击剑、国际跳棋和围棋等十二大项目。",
    "fee": "收费",
    "source": "湖北省体育局崇仁中心",
    "family_friendly": true
  },
  {
    "title": "奔跑吧少年夏令营免费游泳服务",
    "venue": "武汉市40家游泳场馆",
    "city": "wuhan",
    "start_date": "2026-07-15",
    "end_date": "2026-08-03",
    "link": "https://news.hubeidaily.net/mobile/c_5753601.html",
    "description": "全市义务教育阶段中小学生通过线上预约家长陪同入场，40家指定场馆免费游泳20天，每天9:00-11:00、15:00-17:00两个时段。",
    "fee": "免费需预约",
    "source": "武汉市体育局",
    "family_friendly": true
  },
  {
    "title": "光谷暑期体育场馆14天免费开放",
    "venue": "东湖高新区多家运动场馆",
    "city": "wuhan",
    "start_date": "2026-07-15",
    "end_date": "2026-07-28",
    "link": "https://news.hubeidaily.net/mobile/c_5753601.html",
    "description": "涵盖篮球足球羽毛球乒乓球网球匹克球六大热门项目，覆盖光谷多个核心运动场馆，连续14天免费开放。",
    "fee": "免费需预约",
    "source": "东湖高新区文旅体局",
    "family_friendly": true
  },
  {
    "title": "武汉大学-生命科学线下研学营",
    "venue": "武汉大学生命科学学院",
    "city": "wuhan",
    "start_date": "2026-07-18",
    "end_date": "2026-07-21",
    "link": "https://www.dengfengpingtai.com/#/layout/laboratory/onlineActivities?id=1331e65d07993ee4277b79a3ae00ef965a301",
    "description": "走进武大生命科学，参与植物动物分子生物学三大实验，探访杂交水稻和高致病性病毒两个全国重点实验室，感受最美大学文化。",
    "fee": "收费",
    "source": "武汉大学登峰平台",
    "family_friendly": true
  },
  {
    "title": "华中科技大学能源学科线上研学营",
    "venue": "华中科技大学能源与动力工程学院",
    "city": "wuhan",
    "start_date": "2026-08-14",
    "end_date": "2026-08-14",
    "link": "https://www.dengfengpingtai.com/news/d/record/298.html",
    "description": "煤燃烧与低碳利用全国重点实验室主办，学习风能氢能核能在能源转型中的角色，认识储能构建新型能源结构的重要作用。",
    "fee": "免费需报名",
    "source": "华中科技大学登峰平台",
    "family_friendly": true
  },
  {
    "title": "中国地质大学地质探秘荆楚寻韵研学营",
    "venue": "中国地质大学（武汉）",
    "city": "wuhan",
    "start_date": "2026-07-20",
    "end_date": "2026-08-05",
    "link": "https://yjxy.cug.edu.cn/info/1024/8554.htm",
    "description": "4天3晚封闭式研学，逸夫博物馆探秘、南望山科考、矿物实验室实操、地大校园深度探访、东湖地质地貌观察。",
    "fee": "收费",
    "source": "中国地质大学（武汉）",
    "family_friendly": true
  },
  {
    "title": "王牌工科华科武大深度科创营",
    "venue": "武汉大学/华中科技大学",
    "city": "wuhan",
    "start_date": "2026-07-25",
    "end_date": "2026-08-15",
    "link": "https://wenlv.xdf.cn/storedetail/6668.html",
    "description": "6天5晚华科武大985高校成长体验，机械光电遥感人工智能4大王牌工科探访，官网唯一编号证书支持综评。",
    "fee": "收费",
    "source": "新东方文旅",
    "family_friendly": true
  },
  {
    "title": "中科院水生所水生生物学科学夏令营",
    "venue": "中国科学院水生生物研究所",
    "city": "wuhan",
    "start_date": "2026-07-14",
    "end_date": "2026-07-17",
    "link": "http://ihb.cas.cn/edu/kjrh/dxsxlysqxx/202606/t20260612_8227701.html",
    "description": "参观水生所科研园区，聆听科研讲座，与专家导师面对面交流，了解水生生物多样性与资源保护、淡水生态学等方向。",
    "fee": "免费（大学生夏令营）",
    "source": "中国科学院水生生物研究所",
    "family_friendly": true
  },
  {
    "title": "中科院武汉植物园大学生夏令营",
    "venue": "中国科学院武汉植物园",
    "city": "wuhan",
    "start_date": "2026-07-13",
    "end_date": "2026-07-17",
    "link": "https://www.wbgcas.cn/yjsjy/zsxx/sszs/202606/t20260622_8231706.html",
    "description": "专家学术讲座、招生政策宣讲、与导师及研究生面对面交流、参观实验室等活动，免费提供活动期间食宿。",
    "fee": "免费",
    "source": "中国科学院武汉植物园",
    "family_friendly": true
  },
  {
    "title": "带你看世界少年筑梦行公益研学活动",
    "venue": "东湖风景区/湖北省博物馆",
    "city": "wuhan",
    "start_date": "2026-07-08",
    "end_date": "2026-08-31",
    "link": "http://m.toutiao.com/group/7660499766404563507/",
    "description": "组织乡镇学生走进中科院武汉植物园、东湖绿道、湖北省博物馆，三天两夜沉浸式研学，开阔视野启迪心智。",
    "fee": "免费（公益项目）",
    "source": "湖北省委社会工作部",
    "family_friendly": true
  },
  {
    "title": "东湖帆船公园皮划艇体验",
    "venue": "东湖帆船公园",
    "city": "wuhan",
    "start_date": "2026-07-01",
    "end_date": "2026-08-31",
    "link": "http://www.cytong.cn/application/viewpointview?id=257",
    "description": "皮划艇观光拍照打卡，6岁以上120cm以上可体验，6-14岁需成人陪同，专业教练指导安全有保障。",
    "fee": "收费",
    "source": "东湖帆船公园",
    "family_friendly": true
  },
  {
    "title": "东湖水上卡丁船极速体验",
    "venue": "东湖帆船基地",
    "city": "wuhan",
    "start_date": "2026-07-01",
    "end_date": "2026-08-31",
    "link": "https://ctdsbepaper.hubeidaily.net/pad/content/202607/15/content_353304.html",
    "description": "赛道全长近2公里，右脚踩油门双手握方向盘，轻轻一拧船贴水面飞出去，转弯时船尾甩出漂亮水花。",
    "fee": "收费",
    "source": "东湖帆船基地",
    "family_friendly": true
  },
  {
    "title": "东湖观光氦气球高空俯瞰",
    "venue": "东湖风景区",
    "city": "wuhan",
    "start_date": "2026-07-01",
    "end_date": "2026-08-31",
    "link": "https://ctdsbepaper.hubeidaily.net/pad/content/202607/15/content_353304.html",
    "description": "直径23米可同时容纳30人，垂直升空150米，360度俯瞰东湖全景，夜航18:00-21:00日落时段最佳。",
    "fee": "收费",
    "source": "东湖风景区",
    "family_friendly": true
  },
  {
    "title": "木兰胜天森林漂流不限次畅玩",
    "venue": "木兰胜天旅游景区",
    "city": "wuhan",
    "start_date": "2026-07-01",
    "end_date": "2026-08-31",
    "link": "http://m.toutiao.com/group/7658228015800877620/",
    "description": "藏在山林深处原生态森林漂流，全程林荫覆盖清凉无暴晒，水流缓急适中老人小孩都能玩，购票不限次数漂流。",
    "fee": "收费",
    "source": "木兰胜天景区",
    "family_friendly": true
  },
  {
    "title": "武汉园博园音浪嘉年华暨汉口里竹床文化季",
    "venue": "武汉园博园",
    "city": "wuhan",
    "start_date": "2026-07-01",
    "end_date": "2026-08-30",
    "link": "http://m.toutiao.com/group/7662291843161293363/",
    "description": "夏夜全天嗨，东门入园时间延长至21:00，暑期畅玩卡单人亲子票多种选择，音乐演出加竹床文化体验。",
    "fee": "收费",
    "source": "武汉园博园",
    "family_friendly": true
  },
  {
    "title": "东湖智能游船夜航观光",
    "venue": "东湖风景区",
    "city": "wuhan",
    "start_date": "2026-07-01",
    "end_date": "2026-08-31",
    "link": "https://ctdsbepaper.hubeidaily.net/pad/content/202607/15/content_353304.html",
    "description": "搭载毫米波雷达与激光雷达可自主出航自主避障，夜航17:00-19:45，沿东湖绿道至渔光桥折返全程约30分钟。",
    "fee": "收费",
    "source": "东湖风景区",
    "family_friendly": true
  },
  {
    "title": "青少年宫水上世界暑期开放",
    "venue": "武汉市青少年宫水上世界",
    "city": "wuhan",
    "start_date": "2026-06-01",
    "end_date": "2026-08-31",
    "link": "https://www.qianggen.net/2009/tuan85158/",
    "description": "22000平方米超大乐园，从易到难8个玩水区，浅水区动物造型喷水装置，飓风湾时光穿梭大滑梯惊险刺激。",
    "fee": "收费",
    "source": "武汉市青少年宫水上世界",
    "family_friendly": true
  },
  {
    "title": "武汉市少年儿童图书馆阳光阅读医院行",
    "venue": "武汉儿童医院/协和医院/同济医院光谷院区",
    "city": "wuhan",
    "start_date": "2026-07-01",
    "end_date": "2026-08-31",
    "link": "https://m.sohu.com/a/1042110965_121106908/",
    "description": "在武汉儿童医院、协和医院和同济医院光谷院区开展阅读关爱活动，为住院患儿送去书香陪伴。",
    "fee": "免费",
    "source": "武汉市少年儿童图书馆",
    "family_friendly": true
  },
  {
    "title": "知行合一美育未来暑期研学实践营",
    "venue": "全市各新华书店门店",
    "city": "wuhan",
    "start_date": "2026-07-15",
    "end_date": "2026-08-31",
    "link": "http://m.toutiao.com/group/7663313279355290166/",
    "description": "全天托管型、主题工作坊型、AI特色型、非遗传承型四种模式的研学营，覆盖全市新华书店。",
    "fee": "收费",
    "source": "武汉市新华书店",
    "family_friendly": true
  },
  {
    "title": "江夏区博物馆湖泗窑古瓷文化互动体验",
    "venue": "江夏区博物馆",
    "city": "wuhan",
    "start_date": "2026-07-01",
    "end_date": "2026-08-31",
    "link": "http://m.toutiao.com/group/7659744832406946304/",
    "description": "2900平方米展厅300余件文物，全息投影智能触控互动设备，可体验文物数字拓印、京剧脸谱换装等趣味项目。",
    "fee": "免费",
    "source": "江夏区博物馆",
    "family_friendly": true
  },
  {
    "title": "美术馆琴台馆暑期艺术展览",
    "venue": "武汉美术馆琴台馆",
    "city": "wuhan",
    "start_date": "2026-07-01",
    "end_date": "2026-08-31",
    "link": "http://m.toutiao.com/group/7659744832406946304/",
    "description": "全程室内全覆盖不受天气影响，展览更新频率高常年轮换，现当代绘画装置艺术新媒体艺术主题多元。",
    "fee": "免费需预约",
    "source": "武汉美术馆",
    "family_friendly": true
  },
  {
    "title": "长江人艺自然科学儿童音乐剧《美丽生命》",
    "venue": "湖北剧院小剧场",
    "city": "wuhan",
    "start_date": "2026-07-11",
    "end_date": "2026-07-11",
    "link": "http://m.toutiao.com/group/7657843230155604520/",
    "description": "自然科学主题儿童音乐剧，将自然生命科学知识融入音乐剧情，在艺术欣赏中学习科学知识。",
    "fee": "收费",
    "source": "湖北剧院/长江人艺",
    "family_friendly": true
  },
  {
    "title": "长江人艺神话儿童剧《射日小英雄》",
    "venue": "湖北剧院小剧场",
    "city": "wuhan",
    "start_date": "2026-07-18",
    "end_date": "2026-07-19",
    "link": "http://m.toutiao.com/group/7657843230155604520/",
    "description": "后羿射日经典神话改编儿童剧，讲述英雄成长克服困难的故事，传递勇气与担当精神。",
    "fee": "收费",
    "source": "湖北剧院/长江人艺",
    "family_friendly": true
  },
  {
    "title": "超能水手1天周末营——帆船皮划艇双体验",
    "venue": "东湖帆船公园",
    "city": "wuhan",
    "start_date": "2026-07-01",
    "end_date": "2026-08-31",
    "link": "https://m.xialingying.cc/chizi/course/1663035013.html",
    "description": "帆船初识课加皮划艇初识课加绳结科目，7-12周岁青少年，学习帆船结构原理实操驾驶，皮划艇直行转向停船技巧。",
    "fee": "收费",
    "source": "武汉大海阳光帆船俱乐部",
    "family_friendly": true
  },
  {
    "title": "东湖绿道森林烤场亲子烧烤露营",
    "venue": "东湖马鞍山森林公园",
    "city": "wuhan",
    "start_date": "2026-07-01",
    "end_date": "2026-08-31",
    "link": "https://ctdsbepaper.hubeidaily.net/pad/content/202607/15/content_353304.html",
    "description": "3.7万平方米森林烤场森林覆盖率80%，可同时容纳2000余人，台球羽毛球射箭沉浸式KTV等娱乐项目丰富。",
    "fee": "收费",
    "source": "东湖风景区",
    "family_friendly": true
  },
  {
    "title": "木兰天池潮趣端午传统文化体验",
    "venue": "木兰天池景区",
    "city": "wuhan",
    "start_date": "2026-06-19",
    "end_date": "2026-06-21",
    "link": "https://whwb.cjn.cn/h5/html5/2026-06/17/content_48088_3543099.htm",
    "description": "背《离骚》免费入园，包粽子DIY香囊好运投壶及龙舟表演，传统文化沉浸式体验。",
    "fee": "免费（背离骚免票）",
    "source": "木兰天池景区",
    "family_friendly": true
  },
  {
    "title": "清凉寨汉服民俗体验季",
    "venue": "木兰清凉寨景区",
    "city": "wuhan",
    "start_date": "2026-06-19",
    "end_date": "2026-08-31",
    "link": "https://whwb.cjn.cn/h5/html5/2026-06/17/content_48088_3543099.htm",
    "description": "沐兰汤点雄黄射五毒编五彩绳等汉服民俗体验，非遗叶画馆萤火虫生态基地及许愿河灯活动增添夏日意趣。",
    "fee": "收费",
    "source": "木兰清凉寨景区",
    "family_friendly": true
  },
  {
    "title": "东湖亲子龙舟竞渡活动",
    "venue": "东湖听涛水上运动中心",
    "city": "wuhan",
    "start_date": "2026-06-19",
    "end_date": "2026-06-20",
    "link": "https://whwb.cjn.cn/h5/html5/2026-06/17/content_48088_3543099.htm",
    "description": "端午假期东湖亲子龙舟竞渡，家庭组队参与龙舟比赛，体验传统水上运动乐趣。",
    "fee": "收费",
    "source": "东湖风景区",
    "family_friendly": true
  },
  {
    "title": "武汉动物园夏日观赏季",
    "venue": "武汉动物园",
    "city": "wuhan",
    "start_date": "2026-07-01",
    "end_date": "2026-08-31",
    "link": "http://m.toutiao.com/group/7654104067949462067/",
    "description": "全新改造后的武汉动物园，大熊猫、金丝猴、长颈鹿等多种动物观赏，科普教育亲子游玩。",
    "fee": "收费",
    "source": "武汉动物园",
    "family_friendly": true
  },
  {
    "title": "武汉植物园活体昆虫乐园暑期体验",
    "venue": "武汉植物园",
    "city": "wuhan",
    "start_date": "2026-07-01",
    "end_date": "2026-08-31",
    "link": "http://m.toutiao.com/group/7654104067949462067/",
    "description": "活体昆虫科普展示，MINI科学馆植植屋互动体验，认识各类昆虫学习自然知识。",
    "fee": "收费",
    "source": "武汉植物园",
    "family_friendly": true
  },
  {
    "title": "武汉水生生物博物馆珍稀标本展",
    "venue": "中国科学院水生生物研究所",
    "city": "wuhan",
    "start_date": "2026-07-01",
    "end_date": "2026-08-31",
    "link": "http://m.toutiao.com/group/7654104067949462067/",
    "description": "40万件珍稀标本，白鱀豚淇淇3D打印标本，矛尾鱼白鲟标本，1000多种鱼类展示。",
    "fee": "免费",
    "source": "武汉水生生物博物馆",
    "family_friendly": true
  },
  {
    "title": "汉赛跑跑花园暑期升级雾森溯溪",
    "venue": "汉赛跑跑花园",
    "city": "wuhan",
    "start_date": "2026-07-01",
    "end_date": "2026-08-31",
    "link": "https://ctdsbepaper.hubeidaily.net/pad/content/202607/08/content_352637.html",
    "description": "雾森溯溪区域捞鱼捉虾，亲子双人卡丁车，童话小火车穿行花海与恐龙园区，萌宠互动露营野餐。",
    "fee": "收费",
    "source": "汉赛跑跑花园",
    "family_friendly": true
  },
  {
    "title": "后官湖欢乐水世界暑期开放",
    "venue": "后官湖国家湿地公园",
    "city": "wuhan",
    "start_date": "2026-07-01",
    "end_date": "2026-08-31",
    "link": "https://ctdsbepaper.hubeidaily.net/pad/content/202607/08/content_352637.html",
    "description": "水上飞人摩托艇动力冲浪板动感项目，皮划艇自然探索乐园抓鱼摸虾儿童戏水区。",
    "fee": "收费",
    "source": "后官湖国家湿地公园",
    "family_friendly": true
  },
  {
    "title": "九真山避暑亲子游",
    "venue": "九真山风景区",
    "city": "wuhan",
    "start_date": "2026-07-01",
    "end_date": "2026-08-31",
    "link": "https://ctdsbepaper.hubeidaily.net/pad/content/202607/08/content_352637.html",
    "description": "山林避暑地登山步道全程林荫覆盖，吸氧洗肺躲避酷暑，亲子徒步亲近自然。",
    "fee": "收费",
    "source": "九真山风景区",
    "family_friendly": true
  },
  {
    "title": "WS热雪奇迹卡皮巴拉冰雪奇遇记",
    "venue": "WS热雪奇迹武商梦时代8楼",
    "city": "wuhan",
    "start_date": "2026-07-01",
    "end_date": "2026-08-31",
    "link": "http://m.toutiao.com/group/7662333617879761408/",
    "description": "卡皮巴拉小黄豚IP与-6℃恒温室内雪场融合，4大冰雪主题区域，集章打卡兑换周边，免费新手滑雪公开课。",
    "fee": "收费",
    "source": "WS热雪奇迹",
    "family_friendly": true
  },
  {
    "title": "木兰山水世界水上乐园",
    "venue": "木兰山水世界",
    "city": "wuhan",
    "start_date": "2026-06-27",
    "end_date": "2026-08-31",
    "link": "http://m.toutiao.com/group/7661634262914908678/",
    "description": "5万㎡超大水上乐园，全园大面积遮阳棚，缓坡儿童滑梯3米造浪海啸池环形休闲漂流河等30+水上设备。",
    "fee": "收费",
    "source": "木兰山水世界",
    "family_friendly": true
  },
  {
    "title": "武汉极地海洋度假区泼水狂欢节",
    "venue": "武汉极地海洋度假区",
    "city": "wuhan",
    "start_date": "2026-06-27",
    "end_date": "2026-08-30",
    "link": "http://m.toutiao.com/group/7661634262914908678/",
    "description": "户外西游NPC领泼，室内22℃恒温海洋世界，电音泼水派对每晚轮番炸场。",
    "fee": "收费",
    "source": "武汉极地海洋度假区",
    "family_friendly": true
  },
  {
    "title": "武汉市青少年宫国学馆暑期素质训练营",
    "venue": "武汉市青少年宫",
    "city": "wuhan",
    "start_date": "2026-07-06",
    "end_date": "2026-08-07",
    "link": "https://m.sohu.com/a/1034317394_121106908/",
    "description": "依托传统国学内容，帮助孩子夯实识字基础，提升自主阅读能力，培养良好阅读习惯，融入礼仪教养。",
    "fee": "收费",
    "source": "武汉市青少年宫",
    "family_friendly": true
  },
  {
    "title": "光谷美术馆四大首展暑期开放",
    "venue": "光谷美术馆",
    "city": "wuhan",
    "start_date": "2026-07-18",
    "end_date": "2026-10-18",
    "link": "http://m.toutiao.com/group/7663369762512077352/",
    "description": "中国国家画院首展、唐宋八大家主题美术展、显微成像艺术展、AI人工智能艺术展四大首展。",
    "fee": "免费需预约",
    "source": "光谷美术馆",
    "family_friendly": true
  },
  {
    "title": "武汉大学云冈石窟特展",
    "venue": "武汉大学万林艺术博物馆",
    "city": "wuhan",
    "start_date": "2026-07-15",
    "end_date": "2026-09-30",
    "link": "http://m.toutiao.com/group/7659246610878087722/",
    "description": "珍贵原生文物加高精度3D打印复刻造像与壁画残件，感受石窟艺术魅力，走进武大校园感受名校氛围。",
    "fee": "免费",
    "source": "武汉大学万林艺术博物馆",
    "family_friendly": true
  },
  {
    "title": "大国少年守护微笑天使长江生态文明实践行",
    "venue": "武汉白鳍豚馆",
    "city": "wuhan",
    "start_date": "2026-07-22",
    "end_date": "2026-07-22",
    "link": "http://m.toutiao.com/group/7657007274824598079/",
    "description": "走进江豚繁育中心，听声辨豚音，江豚行为监测，制作长江微生态瓶，颁发结营证书。6-12岁20组家庭。",
    "fee": "免费",
    "source": "武汉市妇儿中心",
    "family_friendly": true
  },
  {
    "title": "挺膺护家国童心向未来少年儿童国防教育实践行",
    "venue": "武汉大军山国际营地",
    "city": "wuhan",
    "start_date": "2026-07-08",
    "end_date": "2026-07-08",
    "link": "http://m.toutiao.com/group/7657007274824598079/",
    "description": "参观国防教育展厅，高射炮协同发射气炮射击坦克巡游打卡，体验绳索桥体悟长征精神。6-12岁25组家庭。",
    "fee": "免费",
    "source": "武汉市妇儿中心",
    "family_friendly": true
  },
  {
    "title": "东湖绿道观光电瓶车游览",
    "venue": "东湖绿道",
    "city": "wuhan",
    "start_date": "2026-07-01",
    "end_date": "2026-08-31",
    "link": "http://m.toutiao.com/group/7660499766404563507/",
    "description": "从磨山景区南门出发沿湖岸线缓缓前行，开阔湖面错落树林，水鸟掠过湖面，老少皆宜轻松游览。",
    "fee": "收费",
    "source": "东湖风景区",
    "family_friendly": true
  }
]